Workbook

Sheet Cover
B2: Option Care Health (OPCH) – LBO First-Lien Term Loan Credit Model
B3: Question: should we lend into the ~$3.15bn term debt funding CD&R + McKesson's $32.05/share take-private (signed Oct-5-2026, close expected 1H 2027)?
B5: Tab guide
B6: Inputs | C6: Case / structure / SOFR switches, transaction terms, add-back decisions, pricing, Sources & Uses, implied valuation.
B7: Historicals | C7: FY2023–FY2025, H1 2025/26 and LTM Jun-26: income statement, EBITDA rebuild tied to company figures, Underwriting EBITDA (your view), Credit Agreement EBITDA (covenant view), cash flow, balance sheet.
B8: EBITDA_Addbacks | C8: Underwriter EBITDA CARVE bridge: GAAP net income → Baseline EBITDA → Underwriter EBITDA, EBITDAR, Other-net memo, CARVE scorecard, sensitivities.
B9: Cap_Stack | C9: Pro forma capital structure at close, leverage by layer, equity cushion, pre-deal vs pro forma comparison.
B10: Projections | C10: 7-year operating build, interest on floating debt, free cash flow, revolver / TLB / sweep debt schedule.
B11: Credit_Stats | C11: Leverage, coverage, FCCR, liquidity, covenant headroom and distress flags by year.
B12: Recovery | C12: Distressed EV waterfall, recovery and LGD by class, sensitivity grid, expected loss vs spread.
B13: Colour legend
B14: Blue text | C14: Hardcoded input (from filings or assumption) – sources in cell comments
B15: Black text | C15: Formula
B16: Green text | C16: Link to another tab
B17: Yellow fill | C17: Key assumption / judgment call to revisit
B19: Sources
C20: Source: FY2025 Form 10-K (filed Feb-2026), Consolidated Financial Statements. https://www.sec.gov/Archives/edgar/data/1014739/000101473926000008/bios-20251231.htm
C21: Source: FY2023 Form 10-K, Consolidated Balance Sheet / Note: Indebtedness.
C22: Source: Q2 2026 Form 10-Q (six months ended Jun-30-2026). https://www.sec.gov/Archives/edgar/data/0001014739/000101473926000023/bios-20260630.htm
C23: Source: FY2024 earnings release (8-K Ex. 99.1), Adjusted EBITDA reconciliation. https://www.sec.gov/Archives/edgar/data/1014739/000101473925000008/exhibit991-12312024.htm
C24: Source: FY2025 earnings release (8-K Ex. 99.1, Feb-24-2026), Adjusted EBITDA reconciliation.
C25: Source: Q2 2026 earnings release (8-K Ex. 99.1, Jul-29-2026), six-month Adjusted EBITDA reconciliation.
C26: Source: Fourth Amendment to A&R First Lien Credit Agreement (Sep-22-2025), Exhibit A conformed credit agreement.
C27: Source: Form 8-K dated Oct-5-2026 (Merger Agreement with Onyx Bidco / CD&R + McKesson), Item 1.01.
C28: Deal press release (Oct-6-2026): ~$5.8bn EV, ~37% premium, CD&R ~51% / McKesson ~49%, financing from BofA, Barclays, Goldman Sachs, Jefferies, Wells Fargo.
B30: Key open items
C31: • New loan pricing, OID, tranche split, covenants and maturity are NOT public – modelled as assumptions (Inputs). Update at syndication launch.
C32: • Merger proxy (PREM14A/DEFM14A) will add management projections and financing detail – replace operating cases when filed.
C33: • Q3 2026 10-Q / earnings (due ~late Oct-2026) – roll LTM forward to Sep-30-2026.
C34: • PD on Recovery!B53 is a placeholder until the R Monte Carlo is built.
C35: • Two EBITDAs: Underwriting EBITDA drives cash flow, distress and recovery; Credit Agreement EBITDA (per current OPCH credit agreement definitions) drives covenant tests only.

Sheet Inputs
A1: Option Care Health (OPCH) – LBO First-Lien Term Loan: Inputs & Sources/Uses
A2: $ in millions unless noted · Blue = hardcoded input · Black = formula · Green = link to other tab · Yellow = key assumption to revisit
A4: CASE & STRUCTURE SWITCHES
A5: Operating case (1 = Management, 2 = Lender Base, 3 = Downside) | B5: 2 | C5: =CHOOSE(B5,"Management","Lender Base","Downside") -> Lender Base | J5: Switches drive Projections, Credit_Stats and Recovery. Lender Base is the underwriting case.
A6: Capital structure (1 = A: all 1L, 2 = B: 1L + unsecured, 3 = C: 1L + 2L) | B6: 2 | C6: =CHOOSE(B6,"A: All first-lien","B: 1L + unsecured notes","C: 1L + second-lien") -> B: 1L + unsecured notes
A7: SOFR path (1 = Base, 2 = Stress) | B7: 1 | C7: =CHOOSE(B7,"Base SOFR","Stress SOFR") -> Base SOFR
A9: TRANSACTION TERMS
A10: Offer price per share ($) | B10: 32.05
A11: Diluted shares acquired (mm) | B11: 150.4 | C11: Flag: fully diluted may be ~152–153mm (1.85mm unvested restricted stock + 1.37mm options at $25.93 + PSUs, FY2025 10-K). Verify in merger proxy.
A12: Equity commitment – CD&R Fund XII + McKesson ($mm) | B12: 2873.3
A13: Committed term debt ($mm) | B13: 3150
A14: New revolver commitment ($mm) | B14: 500 | C14: Matures yr: | D14: 5
A15: Existing debt refinanced at par ($mm) | B15: 1172.9
A16: Balance sheet cash at signing ($mm) | B16: 193.8
A17: Minimum operating cash ($mm) | B17: 50
A18: Financing fees (% of committed term debt) | B18: 0.0225
A19: OID on first-lien TLB (% of par) | B19: 0.01
A20: M&A advisory, legal & other fees ($mm) | B20: 75
A22: UNDERWRITING EBITDA – ADD-BACK DECISIONS (your judgment)
A23: % of stock-based comp add-back accepted | B23: 0 | J23: Underwriting EBITDA = your own view of real cash earnings (used for distress, FCF, recovery).
A24: % of restructuring/acquisition/integration add-back accepted | B24: 0
A25: % of loss on debt extinguishment accepted | B25: 0
A26: Run-rate synergy add-back – Credit Agreement EBITDA (% of EBITDA) | B26: 0.1 | C26: Cap: | D26: 0.35 | J26: Credit Agreement EBITDA = what the loan documents let the borrower report (used for covenant tests only).
A27: CAPITAL STRUCTURE SCENARIOS ($mm) – tranche split not yet public
A28: Tranche | B28: A: All 1L | C28: B: 1L+Unsec | D28: C: 1L+2L | F28: Selected
A29: First-lien term loan B | B29: 3150 | C29: 2400 | D29: 2400 | F29: =CHOOSE($B$6,B29,C29,D29) -> 2400
A30: Second-lien term loan | B30: 0 | C30: 0 | D30: 750 | F30: =CHOOSE($B$6,B30,C30,D30) -> 0
A31: Senior unsecured notes | B31: 0 | C31: 750 | D31: 0 | F31: =CHOOSE($B$6,B31,C31,D31) -> 750
A32: Total term debt | B32: =SUM(B29:B31) -> 3150 | C32: =SUM(C29:C31) -> 3150 | D32: =SUM(D29:D31) -> 3150 | F32: =SUM(F29:F31) -> 3150 | G32: =IF(ABS(F32-B13)<0.01,"OK – ties to commitment","CHECK") -> OK – ties to commitment
A34: PRICING (assumed – new loan not yet syndicated)
A35: First-lien TLB spread over SOFR | B35: 0.0325
A36: Second-lien TL spread over SOFR | B36: 0.06
A37: Senior unsecured notes fixed coupon | B37: 0.075
A38: Revolver spread over SOFR | B38: 0.03
A39: Revolver undrawn commitment fee | B39: 0.00375
A40: SOFR floor | B40: 0.005
A41: 1L TLB mandatory amortization (% of original par per year) | B41: 0.01
A42: Excess cash flow sweep to 1L TLB | B42: 0.5
A44: SOFR PATH
A45: Year | C45: 2027 | D45: 2028 | E45: 2029 | F45: 2030 | G45: 2031 | H45: 2032 | I45: 2033
A46: Base SOFR | C46: 0.035 | D46: 0.0325 | E46: 0.0325 | F46: 0.0325 | G46: 0.0325 | H46: 0.0325 | I46: 0.0325
A47: Stress SOFR | C47: 0.055 | D47: 0.06 | E47: 0.06 | F47: 0.0575 | G47: 0.055 | H47: 0.0525 | I47: 0.05
A48: Selected SOFR | C48: =CHOOSE($B$7,C46,C47) -> 0.035 | D48: =CHOOSE($B$7,D46,D47) -> 0.0325 | E48: =CHOOSE($B$7,E46,E47) -> 0.0325 | F48: =CHOOSE($B$7,F46,F47) -> 0.0325 | G48: =CHOOSE($B$7,G46,G47) -> 0.0325 | H48: =CHOOSE($B$7,H46,H47) -> 0.0325 | I48: =CHOOSE($B$7,I46,I47) -> 0.0325
A50: OPERATING CASES
A51: Driver | C51: 2027 | D51: 2028 | E51: 2029 | F51: 2030 | G51: 2031 | H51: 2032 | I51: 2033
A52: Revenue growth – Management | C52: 0.07 | D52: 0.07 | E52: 0.07 | F52: 0.07 | G52: 0.07 | H52: 0.07 | I52: 0.07
A53: Revenue growth – Lender Base | C53: 0.05 | D53: 0.05 | E53: 0.045 | F53: 0.045 | G53: 0.04 | H53: 0.04 | I53: 0.04
A54: Revenue growth – Downside | C54: 0.01 | D54: -0.03 | E54: 0 | F54: 0.02 | G54: 0.03 | H54: 0.03 | I54: 0.03
A55: Revenue growth – Selected | C55: =CHOOSE($B$5,C52,C53,C54) -> 0.05 | D55: =CHOOSE($B$5,D52,D53,D54) -> 0.05 | E55: =CHOOSE($B$5,E52,E53,E54) -> 0.045 | F55: =CHOOSE($B$5,F52,F53,F54) -> 0.045 | G55: =CHOOSE($B$5,G52,G53,G54) -> 0.04 | H55: =CHOOSE($B$5,H52,H53,H54) -> 0.04 | I55: =CHOOSE($B$5,I52,I53,I54) -> 0.04
A57: Underwriting EBITDA margin change vs PF LTM – Management | C57: 0.001 | D57: 0.002 | E57: 0.003 | F57: 0.004 | G57: 0.005 | H57: 0.006 | I57: 0.007
A58: Underwriting EBITDA margin change vs PF LTM – Lender Base | C58: 0 | D58: 0 | E58: 0 | F58: 0 | G58: 0 | H58: 0 | I58: 0
A59: Underwriting EBITDA margin change vs PF LTM – Downside | C59: -0.01 | D59: -0.02 | E59: -0.025 | F59: -0.025 | G59: -0.02 | H59: -0.02 | I59: -0.02
A60: Margin change – Selected | C60: =CHOOSE($B$5,C57,C58,C59) -> 0 | D60: =CHOOSE($B$5,D57,D58,D59) -> 0 | E60: =CHOOSE($B$5,E57,E58,E59) -> 0 | F60: =CHOOSE($B$5,F57,F58,F59) -> 0 | G60: =CHOOSE($B$5,G57,G58,G59) -> 0 | H60: =CHOOSE($B$5,H57,H58,H59) -> 0 | I60: =CHOOSE($B$5,I57,I58,I59) -> 0
A62: OTHER OPERATING ASSUMPTIONS
A63: Capex (% of revenue) | B63: 0.0075
A64: D&A for tax purposes (% of revenue) | B64: 0.0125
A65: Net working capital (% of incremental revenue) | B65: 0.054
A66: Cash tax rate | B66: 0.25 | C66: Int. cap: | D66: 0.3 | E66: of Underwriting EBITDA (Sec. 163(j) interest deduction limit)
A67: Cash rent – operating leases (% of revenue) | B67: 0.0054
A68: COVENANT & DISTRESS TRIGGERS
A69: Revolver springing 1L net leverage covenant (x) – on Credit Agreement EBITDA | B69: 7
A70: Distress trigger: FCCR below (x) | B70: 1
A71: Distress trigger: total net leverage above (x) | B71: 7.5
A72: Distress trigger: liquidity below ($mm) | B72: 100
A74: SOURCES & USES AT CLOSE ($mm)
A75: Sources | B75: $mm | C75: % total | E75: Uses | F75: $mm | G75: % total
A76: First-lien term loan B | B76: =F29 -> 2400 | C76: =IF($B$83=0,0,B76/$B$83) -> 0.38603207 | E76: Purchase of equity (price × diluted shares) | F76: =B10*B11 -> 4820.32 | G76: =IF($F$83=0,0,F76/$F$83) -> 0.77533255
A77: Second-lien term loan | B77: =F30 -> 0 | C77: =IF($B$83=0,0,B77/$B$83) -> 0 | E77: Refinance existing 1L TLB + senior notes | F77: =B15 -> 1172.9 | G77: =IF($F$83=0,0,F77/$F$83) -> 0.18865709
A78: Senior unsecured notes | B78: =F31 -> 750 | C78: =IF($B$83=0,0,B78/$B$83) -> 0.12063502 | E78: Financing fees | F78: =B18*B13 -> 70.875 | G78: =IF($F$83=0,0,F78/$F$83) -> 0.01140001
A79: Revolver draw at close | B79: =MAX(0,G87-(SUM(B76:B78)+B80+B81)+B17) -> 0 | C79: =IF($B$83=0,0,B79/$B$83) -> 0 | E79: OID on first-lien TLB | F79: =B19*F29 -> 24 | G79: =IF($F$83=0,0,F79/$F$83) -> 0.0038603207
A80: Sponsor + McKesson equity | B80: =B12 -> 2873.3 | C80: =IF($B$83=0,0,B80/$B$83) -> 0.46216081 | E80: M&A advisory, legal & other | F80: =B20 -> 75 | G80: =IF($F$83=0,0,F80/$F$83) -> 0.012063502
A81: Existing balance sheet cash | B81: =B16 -> 193.8 | C81: =IF($B$83=0,0,B81/$B$83) -> 0.03117209 | E81: Cash to balance sheet at close | F81: =SUM(B76:B81)-G87 -> 54.005 | G81: =IF($F$83=0,0,F81/$F$83) -> 0.0086865259
A83: Total sources | B83: =SUM(B76:B81) -> 6217.1 | C83: =SUM(C76:C81) -> 1 | E83: Total uses | F83: =SUM(F76:F81) -> 6217.1 | G83: =SUM(G76:G81) -> 1
A84: =IF(ABS(B83-F83)<0.01,"Check: sources = uses ✓","Check: SOURCES ≠ USES") -> Check: sources = uses ✓
E87: Uses before cash to balance sheet | G87: =SUM(F76:F80) -> 6163.095
A89: IMPLIED VALUATION & CUSHION
A90: Purchase enterprise value (equity + existing debt – cash) | B90: =F76+B15-B16 -> 5799.42 | C90: Press release: ~$5.8bn EV, ~37% premium
A91: PF LTM Jun-26 Management Adj. EBITDA | B91: =Historicals!G33 -> 467.752
A92: PF LTM Jun-26 Underwriting EBITDA | B92: =Historicals!G43 -> 403.85
A93: Purchase multiple – EV / Management Adj. EBITDA | B93: =IF(B91=0,0,B90/B91) -> 12.398493
A94: Purchase multiple – EV / Underwriting EBITDA | B94: =IF(B92=0,0,B90/B92) -> 14.360332
A95: Total funded debt at close (term debt + revolver draw) | B95: =SUM(B76:B79) -> 3150
A96: Total debt / Management Adj. EBITDA (market-comparable basis) | B96: =IF(B91=0,0,B95/B91) -> 6.7343379
A97: Total debt / Underwriting EBITDA (our risk view) | B97: =IF(B92=0,0,B95/B92) -> 7.7999257
A98: Equity cushion (equity / total capitalization) | B98: =IF((B80+B95)=0,0,B80/(B80+B95)) -> 0.47703086

Sheet Historicals
A1: Historical Financials & EBITDA Adjustments ($mm)
A2: LTM Jun-26 = FY2025 + H1 2026 – H1 2025 · Balance sheet columns show period-end balances (LTM column = Jun-30-2026)
A4: Income statement | B4: FY2023 | C4: FY2024 | D4: FY2025 | E4: H1 2025 | F4: H1 2026 | G4: LTM Jun-26 | H4: Source
A5: Net revenue | B5: 4302.324 | C5: 4998.202 | D5: 5649.519 | E5: 2749.057 | F5: 2793.054 | G5: =D5+F5-E5 -> 5693.516 | H5: Source: FY2025 Form 10-K (filed Feb-2026), Consolidated Financial Statements. https://www.sec.gov/Archives/edgar/data/1014739/000101473926000008/bios-20251231.htm | H1: Source: Q2 2026 Form 10-Q (six months ended Jun-30-2026). https://www.sec.gov/Archives/edgar/data/0001014739/000101473926000023/bios-20260630.htm
A6: Cost of revenue | B6: 3321.101 | C6: 3985.209 | D6: 4561.624 | E6: 2216.962 | F6: 2263.789 | G6: =D6+F6-E6 -> 4608.451 | H6: Source: FY2025 Form 10-K (filed Feb-2026), Consolidated Financial Statements. https://www.sec.gov/Archives/edgar/data/1014739/000101473926000008/bios-20251231.htm | H1: Source: Q2 2026 Form 10-Q (six months ended Jun-30-2026). https://www.sec.gov/Archives/edgar/data/0001014739/000101473926000023/bios-20260630.htm
A7: Gross profit | B7: =B5-B6 -> 981.223 | C7: =C5-C6 -> 1012.993 | D7: =D5-D6 -> 1087.895 | E7: =E5-E6 -> 532.095 | F7: =F5-F6 -> 529.265 | G7: =G5-G6 -> 1085.065
A8: Gross margin | B8: =IF(B5=0,0,B7/B5) -> 0.22806813 | C8: =IF(C5=0,0,C7/C5) -> 0.20267148 | D8: =IF(D5=0,0,D7/D5) -> 0.19256418 | E8: =IF(E5=0,0,E7/E5) -> 0.19355546 | F8: =IF(F5=0,0,F7/F5) -> 0.18949329 | G8: =IF(G5=0,0,G7/G5) -> 0.19057907
A9: Selling, general & administrative | B9: 607.427 | C9: 630.251 | D9: 682.451 | E9: 338.21 | F9: 339.221 | G9: =D9+F9-E9 -> 683.462 | H9: Source: FY2025 Form 10-K (filed Feb-2026), Consolidated Financial Statements. https://www.sec.gov/Archives/edgar/data/1014739/000101473926000008/bios-20251231.htm | H1: Source: Q2 2026 Form 10-Q (six months ended Jun-30-2026). https://www.sec.gov/Archives/edgar/data/0001014739/000101473926000023/bios-20260630.htm
A10: Depreciation & amortization (opex line) | B10: 59.201 | C10: 60.909 | D10: 67.538 | E10: 31.987 | F10: 32.359 | G10: =D10+F10-E10 -> 67.91 | H10: Source: FY2025 Form 10-K (filed Feb-2026), Consolidated Financial Statements. https://www.sec.gov/Archives/edgar/data/1014739/000101473926000008/bios-20251231.htm | H1: Source: Q2 2026 Form 10-Q (six months ended Jun-30-2026). https://www.sec.gov/Archives/edgar/data/0001014739/000101473926000023/bios-20260630.htm
A11: Operating income | B11: =B7-B9-B10 -> 314.595 | C11: =C7-C9-C10 -> 321.833 | D11: =D7-D9-D10 -> 337.906 | E11: =E7-E9-E10 -> 161.898 | F11: =F7-F9-F10 -> 157.685 | G11: =G7-G9-G10 -> 333.693
A12: Interest expense, net | B12: 51.248 | C12: 49.029 | D12: 54.558 | E12: 27.678 | F12: 27.324 | G12: =D12+F12-E12 -> 54.204 | H12: Source: FY2025 Form 10-K (filed Feb-2026), Consolidated Financial Statements. https://www.sec.gov/Archives/edgar/data/1014739/000101473926000008/bios-20251231.htm | H1: Source: Q2 2026 Form 10-Q (six months ended Jun-30-2026). https://www.sec.gov/Archives/edgar/data/0001014739/000101473926000023/bios-20260630.htm
A13: Equity in earnings of joint ventures | B13: 5.53 | C13: 5.964 | D13: 7.409 | E13: 3.124 | F13: 3.393 | G13: =D13+F13-E13 -> 7.678 | H13: Source: FY2025 Form 10-K (filed Feb-2026), Consolidated Financial Statements. https://www.sec.gov/Archives/edgar/data/1014739/000101473926000008/bios-20251231.htm | H1: Source: Q2 2026 Form 10-Q (six months ended Jun-30-2026). https://www.sec.gov/Archives/edgar/data/0001014739/000101473926000023/bios-20260630.htm
A14: Other, net | B14: 89.865 | C14: 4.831 | D14: -7.857 | E14: -4.927 | F14: 1.236 | G14: =D14+F14-E14 -> -1.694 | H14: Source: FY2025 Form 10-K (filed Feb-2026), Consolidated Financial Statements. https://www.sec.gov/Archives/edgar/data/1014739/000101473926000008/bios-20251231.htm | H1: Source: Q2 2026 Form 10-Q (six months ended Jun-30-2026). https://www.sec.gov/Archives/edgar/data/0001014739/000101473926000023/bios-20260630.htm FY2023 includes Amedisys merger termination fee gain.
A15: Pre-tax income | B15: =B11-B12+B13+B14 -> 358.742 | C15: =C11-C12+C13+C14 -> 283.599 | D15: =D11-D12+D13+D14 -> 282.9 | E15: =E11-E12+E13+E14 -> 132.417 | F15: =F11-F12+F13+F14 -> 134.99 | G15: =G11-G12+G13+G14 -> 285.473
A16: Income tax expense | B16: 91.652 | C16: 71.776 | D16: 75.315 | E16: 35.152 | F16: 35.734 | G16: =D16+F16-E16 -> 75.897 | H16: Source: FY2025 Form 10-K (filed Feb-2026), Consolidated Financial Statements. https://www.sec.gov/Archives/edgar/data/1014739/000101473926000008/bios-20251231.htm | H1: Source: Q2 2026 Form 10-Q (six months ended Jun-30-2026). https://www.sec.gov/Archives/edgar/data/0001014739/000101473926000023/bios-20260630.htm
A17: Net income | B17: =B15-B16 -> 267.09 | C17: =C15-C16 -> 211.823 | D17: =D15-D16 -> 207.585 | E17: =E15-E16 -> 97.265 | F17: =F15-F16 -> 99.256 | G17: =G15-G16 -> 209.576
A18: Company-reported net income | B18: 267.09 | C18: 211.823 | D18: 207.585 | E18: 97.265 | F18: 99.256 | G18: =D18+F18-E18 -> 209.576 | H18: Source: FY2025 Form 10-K (filed Feb-2026), Consolidated Financial Statements. https://www.sec.gov/Archives/edgar/data/1014739/000101473926000008/bios-20251231.htm | H1: Source: Q2 2026 Form 10-Q (six months ended Jun-30-2026). https://www.sec.gov/Archives/edgar/data/0001014739/000101473926000023/bios-20260630.htm
A19: Check vs reported net income (should be zero) | B19: =ROUND(B17-B18,3) -> 0 | C19: =ROUND(C17-C18,3) -> 0 | D19: =ROUND(D17-D18,3) -> 0 | E19: =ROUND(E17-E18,3) -> 0 | F19: =ROUND(F17-F18,3) -> 0 | G19: =ROUND(G17-G18,3) -> 0
A20: EBITDA reconciliation | B20: FY2023 | C20: FY2024 | D20: FY2025 | E20: H1 2025 | F20: H1 2026 | G20: LTM Jun-26 | H20: Source
A21: Net income | B21: =B17 -> 267.09 | C21: =C17 -> 211.823 | D21: =D17 -> 207.585 | E21: =E17 -> 97.265 | F21: =F17 -> 99.256 | G21: =G17 -> 209.576
A22: + Interest expense, net | B22: =B12 -> 51.248 | C22: =C12 -> 49.029 | D22: =D12 -> 54.558 | E22: =E12 -> 27.678 | F22: =F12 -> 27.324 | G22: =G12 -> 54.204
A23: + Income tax expense | B23: =B16 -> 91.652 | C23: =C16 -> 71.776 | D23: =D16 -> 75.315 | E23: =E16 -> 35.152 | F23: =F16 -> 35.734 | G23: =G16 -> 75.897
A24: + Depreciation & amortization (total, incl. in cost of revenue) | B24: 62.2 | C24: 63.498 | D24: 70.69 | E24: 33.326 | F24: 34.037 | G24: =D24+F24-E24 -> 71.401 | H24: Source: FY2025 Form 10-K (filed Feb-2026), Consolidated Financial Statements. https://www.sec.gov/Archives/edgar/data/1014739/000101473926000008/bios-20251231.htm Cash flow statement D&A (company uses this figure in its EBITDA).
A25: EBITDA | B25: =SUM(B21:B24) -> 472.19 | C25: =SUM(C21:C24) -> 396.126 | D25: =SUM(D21:D24) -> 408.148 | E25: =SUM(E21:E24) -> 193.421 | F25: =SUM(F21:F24) -> 196.351 | G25: =SUM(G21:G24) -> 411.078
A26: Company-reported EBITDA | B26: 472.19 | C26: 396.126 | D26: 408.148 | E26: 193.421 | F26: 196.351 | G26: =D26+F26-E26 -> 411.078 | H26: Source: FY2024 earnings release (8-K Ex. 99.1), Adjusted EBITDA reconciliation. https://www.sec.gov/Archives/edgar/data/1014739/000101473925000008/exhibit991-12312024.htm | Source: FY2025 earnings release (8-K Ex. 99.1, Feb-24-2026), Adjusted EBITDA reconciliation. | Source: Q2 2026 earnings release (8-K Ex. 99.1, Jul-29-2026), six-month Adjusted EBITDA reconciliation.
A27: Check (should be zero) | B27: =ROUND(B25-B26,3) -> 0 | C27: =ROUND(C25-C26,3) -> 0 | D27: =ROUND(D25-D26,3) -> 0 | E27: =ROUND(E25-E26,3) -> 0 | F27: =ROUND(F25-F26,3) -> 0 | G27: =ROUND(G25-G26,3) -> 0
A29: Management add-backs:
A30: + Stock-based incentive compensation | B30: 30.479 | C30: 36.143 | D30: 39.956 | E30: 19.513 | F30: 18.581 | G30: =D30+F30-E30 -> 39.024 | H30: Source: FY2024 earnings release (8-K Ex. 99.1), Adjusted EBITDA reconciliation. https://www.sec.gov/Archives/edgar/data/1014739/000101473925000008/exhibit991-12312024.htm | Source: FY2025 earnings release (8-K Ex. 99.1, Feb-24-2026), Adjusted EBITDA reconciliation. | Source: Q2 2026 earnings release (8-K Ex. 99.1, Jul-29-2026), six-month Adjusted EBITDA reconciliation.
A31: + Loss on extinguishment of debt | B31: 0 | C31: 0.377 | D31: 4.744 | E31: 0 | F31: 0 | G31: =D31+F31-E31 -> 4.744 | H31: Source: FY2025 earnings release (8-K Ex. 99.1, Feb-24-2026), Adjusted EBITDA reconciliation.
A32: + Restructuring, acquisition, integration & other | B32: -77.486 | C32: 11.143 | D32: 18.436 | E32: 12.85 | F32: 7.32 | G32: =D32+F32-E32 -> 12.906 | H32: FY2023 is negative: Amedisys merger termination fee, net of merger costs (Source: FY2024 earnings release (8-K Ex. 99.1), Adjusted EBITDA reconciliation. https://www.sec.gov/Archives/edgar/data/1014739/000101473925000008/exhibit991-12312024.htm)
A33: Management Adjusted EBITDA | B33: =B25+SUM(B30:B32) -> 425.183 | C33: =C25+SUM(C30:C32) -> 443.789 | D33: =D25+SUM(D30:D32) -> 471.284 | E33: =E25+SUM(E30:E32) -> 225.784 | F33: =F25+SUM(F30:F32) -> 222.252 | G33: =G25+SUM(G30:G32) -> 467.752
A34: Company-reported Adjusted EBITDA | B34: 425.183 | C34: 443.789 | D34: 471.284 | E34: 225.784 | F34: 222.252 | G34: =D34+F34-E34 -> 467.752 | H34: Source: FY2024 earnings release (8-K Ex. 99.1), Adjusted EBITDA reconciliation. https://www.sec.gov/Archives/edgar/data/1014739/000101473925000008/exhibit991-12312024.htm | Source: FY2025 earnings release (8-K Ex. 99.1, Feb-24-2026), Adjusted EBITDA reconciliation. | Source: Q2 2026 earnings release (8-K Ex. 99.1, Jul-29-2026), six-month Adjusted EBITDA reconciliation.
A35: Check (should be zero) | B35: =ROUND(B33-B34,3) -> 0 | C35: =ROUND(C33-C34,3) -> 0 | D35: =ROUND(D33-D34,3) -> 0 | E35: =ROUND(E33-E34,3) -> 0 | F35: =ROUND(F33-F34,3) -> 0 | G35: =ROUND(G33-G34,3) -> 0
A36: Management Adj. EBITDA margin | B36: =IF(B5=0,0,B33/B5) -> 0.098826355 | C36: =IF(C5=0,0,C33/C5) -> 0.088789729 | D36: =IF(D5=0,0,D33/D5) -> 0.083420199 | E36: =IF(E5=0,0,E33/E5) -> 0.082131436 | F36: =IF(F5=0,0,F33/F5) -> 0.079573112 | G36: =IF(G5=0,0,G33/G5) -> 0.08215521
A37: UNDERWRITER EBITDA (CARVE-filtered summary) | B37: FY2023 | C37: FY2024 | D37: FY2025 | E37: H1 2025 | F37: H1 2026 | G37: LTM Jun-26 | H37: Treatment
A38: Baseline EBITDA (GAAP net income + interest + taxes + D&A) | B38: =EBITDA_Addbacks!B10 -> 472.19 | C38: =EBITDA_Addbacks!C10 -> 396.126 | D38: =EBITDA_Addbacks!D10 -> 408.148 | E38: =EBITDA_Addbacks!E10 -> 193.421 | F38: =EBITDA_Addbacks!F10 -> 196.351 | G38: =EBITDA_Addbacks!G10 -> 411.078 | H38: Full bridge, CARVE scorecard and memo detail: EBITDA_Addbacks tab.
A39: Non-operating: strip gains / accepted losses (A1 + A2 + A5) | B39: =EBITDA_Addbacks!B14+EBITDA_Addbacks!B15+EBITDA_Addbacks!B18 -> -110.965 | C39: =EBITDA_Addbacks!C14+EBITDA_Addbacks!C15+EBITDA_Addbacks!C18 -> -5.208 | D39: =EBITDA_Addbacks!D14+EBITDA_Addbacks!D15+EBITDA_Addbacks!D18 -> 0 | E39: =EBITDA_Addbacks!E14+EBITDA_Addbacks!E15+EBITDA_Addbacks!E18 -> 0 | F39: =EBITDA_Addbacks!F14+EBITDA_Addbacks!F15+EBITDA_Addbacks!F18 -> -1.236 | G39: =EBITDA_Addbacks!G14+EBITDA_Addbacks!G15+EBITDA_Addbacks!G18 -> -3.05 | H39: Gains stripped symmetrically; non-operating losses kept unless they pass all five CARVE checks.
A40: Compensation & restructuring accepted (A3 + A4) | B40: =EBITDA_Addbacks!B16+EBITDA_Addbacks!B17 -> 0 | C40: =EBITDA_Addbacks!C16+EBITDA_Addbacks!C17 -> 0 | D40: =EBITDA_Addbacks!D16+EBITDA_Addbacks!D17 -> 0 | E40: =EBITDA_Addbacks!E16+EBITDA_Addbacks!E17 -> 0 | F40: =EBITDA_Addbacks!F16+EBITDA_Addbacks!F17 -> 0 | G40: =EBITDA_Addbacks!G16+EBITDA_Addbacks!G17 -> 0 | H40: SBC and restructuring fail CARVE (Recurring / Excluded) – rejected.
A41: JV earnings to cash basis (A6) | B41: =EBITDA_Addbacks!B19 -> -1.53 | C41: =EBITDA_Addbacks!C19 -> -3.564 | D41: =EBITDA_Addbacks!D19 -> -3.409 | E41: =EBITDA_Addbacks!E19 -> -1.524 | F41: =EBITDA_Addbacks!F19 -> -2.293 | G41: =EBITDA_Addbacks!G19 -> -4.178 | H41: Only JV cash actually received counts.
A42: Synergies & capex reclassification (A7 + A8) | B42: =EBITDA_Addbacks!B20+EBITDA_Addbacks!B21 -> 0 | C42: =EBITDA_Addbacks!C20+EBITDA_Addbacks!C21 -> 0 | D42: =EBITDA_Addbacks!D20+EBITDA_Addbacks!D21 -> 0 | E42: =EBITDA_Addbacks!E20+EBITDA_Addbacks!E21 -> 0 | F42: =EBITDA_Addbacks!F20+EBITDA_Addbacks!F21 -> 0 | G42: =EBITDA_Addbacks!G20+EBITDA_Addbacks!G21 -> 0 | H42: Speculative synergies disallowed; no capex misclassification found.
A43: Underwriting EBITDA | B43: =SUM(B38:B42) -> 359.695 | C43: =SUM(C38:C42) -> 387.354 | D43: =SUM(D38:D42) -> 404.739 | E43: =SUM(E38:E42) -> 191.897 | F43: =SUM(F38:F42) -> 192.822 | G43: =SUM(G38:G42) -> 403.85
A44: Underwriting EBITDA margin | B44: =IF(B5=0,0,B43/B5) -> 0.083604815 | C44: =IF(C5=0,0,C43/C5) -> 0.077498669 | D44: =IF(D5=0,0,D43/D5) -> 0.07164132 | E44: =IF(E5=0,0,E43/E5) -> 0.069804664 | F44: =IF(F5=0,0,F43/F5) -> 0.069036259 | G44: =IF(G5=0,0,G43/G5) -> 0.070931565
A45: Haircut vs Management Adj. EBITDA ($) | B45: =B43-B33 -> -65.488 | C45: =C43-C33 -> -56.435 | D45: =D43-D33 -> -66.545 | E45: =E43-E33 -> -33.887 | F45: =F43-F33 -> -29.43 | G45: =G43-G33 -> -63.902
A46: Haircut vs Management Adj. EBITDA (%) | B46: =IF(B33=0,0,B45/B33) -> -0.15402309 | C46: =IF(C33=0,0,C45/C33) -> -0.12716629 | D46: =IF(D33=0,0,D45/D33) -> -0.14119936 | E46: =IF(E33=0,0,E45/E33) -> -0.15008592 | F46: =IF(F33=0,0,F45/F33) -> -0.13241726 | G46: =IF(G33=0,0,G45/G33) -> -0.13661513
A48: Add-back recurrence test
A49: SBC as % of Management Adj. EBITDA | B49: =IF(B33=0,0,B30/B33) -> 0.071684428 | C49: =IF(C33=0,0,C30/C33) -> 0.081441856 | D49: =IF(D33=0,0,D30/D33) -> 0.084781151 | E49: =IF(E33=0,0,E30/E33) -> 0.086423307 | F49: =IF(F33=0,0,F30/F33) -> 0.083603297 | G49: =IF(G33=0,0,G30/G33) -> 0.083428826
A50: Restructuring & other as % of Management Adj. EBITDA | B50: =IF(B33=0,0,B32/B33) -> -0.18224153 | C50: =IF(C33=0,0,C32/C33) -> 0.025108779 | D50: =IF(D33=0,0,D32/D33) -> 0.039118663 | E50: =IF(E33=0,0,E32/E33) -> 0.056912802 | F50: =IF(F33=0,0,F32/F33) -> 0.032935587 | G50: =IF(G33=0,0,G32/G33) -> 0.027591544
A52: Cash flow | B52: FY2023 | C52: FY2024 | D52: FY2025 | E52: H1 2025 | F52: H1 2026 | G52: LTM Jun-26 | H52: Source
A53: Cash from operations | B53: 371.295 | C53: 323.392 | D53: 258.447 | E53: 83.119 | F53: 171.485 | G53: =D53+F53-E53 -> 346.813 | H53: Source: FY2025 Form 10-K (filed Feb-2026), Consolidated Financial Statements. https://www.sec.gov/Archives/edgar/data/1014739/000101473926000008/bios-20251231.htm | H1: Source: Q2 2026 Form 10-Q (six months ended Jun-30-2026). https://www.sec.gov/Archives/edgar/data/0001014739/000101473926000023/bios-20260630.htm
A54: Capital expenditures | B54: 41.866 | C54: 35.606 | D54: 41.307 | E54: 18.466 | F54: 20.123 | G54: =D54+F54-E54 -> 42.964 | H54: Source: FY2025 Form 10-K (filed Feb-2026), Consolidated Financial Statements. https://www.sec.gov/Archives/edgar/data/1014739/000101473926000008/bios-20251231.htm | H1: Source: Q2 2026 Form 10-Q (six months ended Jun-30-2026). https://www.sec.gov/Archives/edgar/data/0001014739/000101473926000023/bios-20260630.htm
A55: Free cash flow (CFO – capex) | B55: =B53-B54 -> 329.429 | C55: =C53-C54 -> 287.786 | D55: =D53-D54 -> 217.14 | E55: =E53-E54 -> 64.653 | F55: =F53-F54 -> 151.362 | G55: =G53-G54 -> 303.849
A56: Capex % of revenue | B56: =IF(B5=0,0,B54/B5) -> 0.0097310198 | C56: =IF(C5=0,0,C54/C5) -> 0.0071237617 | D56: =IF(D5=0,0,D54/D5) -> 0.0073115959 | E56: =IF(E5=0,0,E54/E5) -> 0.0067172125 | F56: =IF(F5=0,0,F54/F5) -> 0.0072046584 | G56: =IF(G5=0,0,G54/G5) -> 0.0075461279
A57: FCF conversion (FCF / Underwriting EBITDA) | B57: =IF(B43=0,0,B55/B43) -> 0.91585649 | C57: =IF(C43=0,0,C55/C43) -> 0.74295347 | D57: =IF(D43=0,0,D55/D43) -> 0.53649389 | E57: =IF(E43=0,0,E55/E43) -> 0.33691512 | F57: =IF(F43=0,0,F55/F43) -> 0.78498304 | G57: =IF(G43=0,0,G55/G43) -> 0.75238083
A58: Business acquisitions | B58: 12.494 | C58: 0 | D58: 117.247 | E58: 117.247 | F58: 0 | G58: =D58+F58-E58 -> 0 | H58: Source: FY2025 Form 10-K (filed Feb-2026), Consolidated Financial Statements. https://www.sec.gov/Archives/edgar/data/1014739/000101473926000008/bios-20251231.htm | H1: Source: Q2 2026 Form 10-Q (six months ended Jun-30-2026). https://www.sec.gov/Archives/edgar/data/0001014739/000101473926000023/bios-20260630.htm
A59: Share repurchases | B59: 250.261 | C59: 252.726 | D59: 309.951 | E59: 152.429 | F59: 170.545 | G59: =D59+F59-E59 -> 328.067 | H59: Source: FY2025 Form 10-K (filed Feb-2026), Consolidated Financial Statements. https://www.sec.gov/Archives/edgar/data/1014739/000101473926000008/bios-20251231.htm | H1: Source: Q2 2026 Form 10-Q (six months ended Jun-30-2026). https://www.sec.gov/Archives/edgar/data/0001014739/000101473926000023/bios-20260630.htm
A60: Cash interest paid | B60: 69.804 | C60: 71.553 | D60: 64.658 | E60: 32.526 | F60: 30.377 | G60: =D60+F60-E60 -> 62.509 | H60: Source: FY2025 Form 10-K (filed Feb-2026), Consolidated Financial Statements. https://www.sec.gov/Archives/edgar/data/1014739/000101473926000008/bios-20251231.htm | H1: Source: Q2 2026 Form 10-Q (six months ended Jun-30-2026). https://www.sec.gov/Archives/edgar/data/0001014739/000101473926000023/bios-20260630.htm
A61: Cash taxes paid | B61: 75.241 | C61: 64.522 | D61: 67.287 | E61: 39.436 | F61: 34.306 | G61: =D61+F61-E61 -> 62.157 | H61: Source: FY2025 Form 10-K (filed Feb-2026), Consolidated Financial Statements. https://www.sec.gov/Archives/edgar/data/1014739/000101473926000008/bios-20251231.htm | H1: Source: Q2 2026 Form 10-Q (six months ended Jun-30-2026). https://www.sec.gov/Archives/edgar/data/0001014739/000101473926000023/bios-20260630.htm
A63: Balance sheet & credit stats | B63: Dec-23 | C63: Dec-24 | D63: Dec-25 | F63: Jun-26 | G63: LTM Jun-26 | H63: Source
A64: Cash and cash equivalents | B64: 343.849 | C64: 412.565 | D64: 232.624 | F64: 193.767 | G64: =F64 -> 193.767 | H64: Source: FY2023 Form 10-K, Consolidated Balance Sheet / Note: Indebtedness. (Dec-23) | Source: FY2025 Form 10-K (filed Feb-2026), Consolidated Financial Statements. https://www.sec.gov/Archives/edgar/data/1014739/000101473926000008/bios-20251231.htm (Dec-24, Dec-25) | Source: Q2 2026 Form 10-Q (six months ended Jun-30-2026). https://www.sec.gov/Archives/edgar/data/0001014739/000101473926000023/bios-20260630.htm (Jun-26)
A65: Accounts receivable, net | B65: 377.658 | C65: 409.733 | D65: 473.566 | F65: 511.507 | G65: =F65 -> 511.507 | H65: Source: FY2023 Form 10-K, Consolidated Balance Sheet / Note: Indebtedness. (Dec-23) | Source: FY2025 Form 10-K (filed Feb-2026), Consolidated Financial Statements. https://www.sec.gov/Archives/edgar/data/1014739/000101473926000008/bios-20251231.htm (Dec-24, Dec-25) | Source: Q2 2026 Form 10-Q (six months ended Jun-30-2026). https://www.sec.gov/Archives/edgar/data/0001014739/000101473926000023/bios-20260630.htm (Jun-26)
A66: Inventories | B66: 274.004 | C66: 388.131 | D66: 471.149 | F66: 399.605 | G66: =F66 -> 399.605 | H66: Source: FY2023 Form 10-K, Consolidated Balance Sheet / Note: Indebtedness. (Dec-23) | Source: FY2025 Form 10-K (filed Feb-2026), Consolidated Financial Statements. https://www.sec.gov/Archives/edgar/data/1014739/000101473926000008/bios-20251231.htm (Dec-24, Dec-25) | Source: Q2 2026 Form 10-Q (six months ended Jun-30-2026). https://www.sec.gov/Archives/edgar/data/0001014739/000101473926000023/bios-20260630.htm (Jun-26)
A67: Accounts payable | B67: 426.513 | C67: 610.779 | D67: 639.829 | F67: 639.767 | G67: =F67 -> 639.767 | H67: Source: FY2023 Form 10-K, Consolidated Balance Sheet / Note: Indebtedness. (Dec-23) | Source: FY2025 Form 10-K (filed Feb-2026), Consolidated Financial Statements. https://www.sec.gov/Archives/edgar/data/1014739/000101473926000008/bios-20251231.htm (Dec-24, Dec-25) | Source: Q2 2026 Form 10-Q (six months ended Jun-30-2026). https://www.sec.gov/Archives/edgar/data/0001014739/000101473926000023/bios-20260630.htm (Jun-26)
A68: Net working capital (AR + inventory – AP) | B68: =B65+B66-B67 -> 225.149 | C68: =C65+C66-C67 -> 187.085 | D68: =D65+D66-D67 -> 304.886 | F68: =F65+F66-F67 -> 271.345 | G68: =G65+G66-G67 -> 271.345
A69: Total debt (principal: 1L TLB + senior notes) | B69: 1088 | C69: 1131.617 | D69: 1176.305 | F69: 1172.915 | G69: =F69 -> 1172.915 | H69: Source: FY2023 Form 10-K, Consolidated Balance Sheet / Note: Indebtedness. (Dec-23) | Source: FY2025 Form 10-K (filed Feb-2026), Consolidated Financial Statements. https://www.sec.gov/Archives/edgar/data/1014739/000101473926000008/bios-20251231.htm (Dec-24, Dec-25) | Source: Q2 2026 Form 10-Q (six months ended Jun-30-2026). https://www.sec.gov/Archives/edgar/data/0001014739/000101473926000023/bios-20260630.htm (Jun-26)
A70: Net debt | B70: =B69-B64 -> 744.151 | C70: =C69-C64 -> 719.052 | D70: =D69-D64 -> 943.681 | F70: =F69-F64 -> 979.148 | G70: =G69-G64 -> 979.148
A71: Total stockholders' equity | B71: 1421.672 | C71: 1404.238 | D71: 1326.393 | F71: 1259.898 | G71: =F71 -> 1259.898 | H71: Source: FY2023 Form 10-K, Consolidated Balance Sheet / Note: Indebtedness. (Dec-23) | Source: FY2025 Form 10-K (filed Feb-2026), Consolidated Financial Statements. https://www.sec.gov/Archives/edgar/data/1014739/000101473926000008/bios-20251231.htm (Dec-24, Dec-25) | Source: Q2 2026 Form 10-Q (six months ended Jun-30-2026). https://www.sec.gov/Archives/edgar/data/0001014739/000101473926000023/bios-20260630.htm (Jun-26)
A73: Gross leverage – Management Adj. EBITDA | B73: =IF(B33=0,0,B69/B33) -> 2.5588982 | C73: =IF(C33=0,0,C69/C33) -> 2.5498987 | D73: =IF(D33=0,0,D69/D33) -> 2.4959579 | G73: =IF(G33=0,0,G69/G33) -> 2.5075574 | H73: Pre-LBO standalone credit profile – compare with Cap_Stack pro forma.
A74: Gross leverage – Underwriting EBITDA | B74: =IF(B43=0,0,B69/B43) -> 3.0247849 | C74: =IF(C43=0,0,C69/C43) -> 2.9214026 | D74: =IF(D43=0,0,D69/D43) -> 2.9063298 | G74: =IF(G43=0,0,G69/G43) -> 2.9043333
A75: Net leverage – Underwriting EBITDA | B75: =IF(B43=0,0,B70/B43) -> 2.0688389 | C75: =IF(C43=0,0,C70/C43) -> 1.8563175 | D75: =IF(D43=0,0,D70/D43) -> 2.3315791 | G75: =IF(G43=0,0,G70/G43) -> 2.4245339
A76: Interest coverage (Underwriting EBITDA / interest) | B76: =IF(B12=0,0,B43/B12) -> 7.0187129 | C76: =IF(C12=0,0,C43/C12) -> 7.9005079 | D76: =IF(D12=0,0,D43/D12) -> 7.4185087 | G76: =IF(G12=0,0,G43/G12) -> 7.4505572
A77: NWC % of revenue | B77: =IF(B5=0,0,B68/B5) -> 0.052331949 | C77: =IF(C5=0,0,C68/C5) -> 0.03743046 | D77: =IF(D5=0,0,D68/D5) -> 0.053966718 | G77: =IF(G5=0,0,G68/G5) -> 0.0476586
A79: CREDIT AGREEMENT EBITDA (covenant basis) | B79: FY2023 | C79: FY2024 | D79: FY2025 | E79: H1 2025 | F79: H1 2026 | G79: LTM Jun-26 | H79: Credit agreement clause
A80: EBITDA (GAAP-based) | B80: =B25 -> 472.19 | C80: =C25 -> 396.126 | D80: =D25 -> 408.148 | E80: =E25 -> 193.421 | F80: =F25 -> 196.351 | G80: =G25 -> 411.078 | H80: Net income + interest + taxes + D&A (CNI base).
A81: + Stock-based compensation | B81: =B30 -> 30.479 | C81: =C30 -> 36.143 | D81: =D30 -> 39.956 | E81: =E30 -> 19.513 | F81: =F30 -> 18.581 | G81: =G30 -> 39.024 | H81: CNI (n), (q): equity-based compensation excluded.
A82: + Loss on extinguishment of debt | B82: =B31 -> 0 | C82: =C31 -> 0.377 | D82: =D31 -> 4.744 | E82: =E31 -> 0 | F82: =F31 -> 0 | G82: =G31 -> 4.744 | H82: CNI (j): gains/losses on extinguishment of debt excluded.
A83: + Restructuring, transaction & integration (gains also removed) | B83: =B32 -> -77.486 | C83: =C32 -> 11.143 | D83: =D32 -> 18.436 | E83: =E32 -> 12.85 | F83: =F32 -> 7.32 | G83: =G32 -> 12.906 | H83: CNI (a), (c): non-recurring items, restructuring, integration, transaction costs excluded – both losses AND gains.
A84: – Equity in earnings of joint ventures | B84: =-B13 -> -5.53 | C84: =-C13 -> -5.964 | D84: =-D13 -> -7.409 | E84: =-E13 -> -3.124 | F84: =-F13 -> -3.393 | G84: =-G13 -> -7.678 | H84: CNI (g): equity-method income excluded…
A85: + Cash distributions received from joint ventures | B85: 4 | C85: 2.4 | D85: 4 | E85: 1.6 | F85: 1.1 | G85: =D85+F85-E85 -> 3.5 | H85: CNI (g): equity-method income replaced by cash actually received. Source: cash flow statements (Source: FY2025 Form 10-K (filed Feb-2026), Consolidated Financial Statements. https://www.sec.gov/Archives/edgar/data/1014739/000101473926000008/bios-20251231.htm | Source: Q2 2026 Form 10-Q (six months ended Jun-30-2026). https://www.sec.gov/Archives/edgar/data/0001014739/000101473926000023/bios-20260630.htm)
A86: Credit Agreement EBITDA before run-rate synergies | B86: =SUM(B80:B85) -> 423.653 | C86: =SUM(C80:C85) -> 440.225 | D86: =SUM(D80:D85) -> 467.875 | E86: =SUM(E80:E85) -> 224.26 | F86: =SUM(F80:F85) -> 219.959 | G86: =SUM(G80:G85) -> 463.574
A87: + Run-rate synergies (PF LTM only) | B87: 0 | C87: 0 | D87: 0 | E87: 0 | F87: 0 | G87: =G86*MIN(Inputs!$B$26,Inputs!$D$26/(1-Inputs!$D$26)) -> 46.3574 | H87: EBITDA (a)(vii): Inputs!B26, capped so synergies ≤ 35% of post-add-back EBITDA (Inputs!D26).
A88: Credit Agreement EBITDA (covenant basis) | B88: =B86+B87 -> 423.653 | C88: =C86+C87 -> 440.225 | D88: =D86+D87 -> 467.875 | E88: =E86+E87 -> 224.26 | F88: =F86+F87 -> 219.959 | G88: =G86+G87 -> 509.9314 | H88: Not captured (not visible in filings): QoE add-backs (a)(xi), other non-cash charges CNI (l), Section 1.08 pro forma acquisitions. True covenant EBITDA is likely HIGHER.
A89: Uplift vs Underwriting EBITDA (%) | B89: =IF(B43=0,0,B88/B43-1) -> 0.17781176 | C89: =IF(C43=0,0,C88/C43-1) -> 0.13649272 | D89: =IF(D43=0,0,D88/D43-1) -> 0.15599189 | E89: =IF(E43=0,0,E88/E43-1) -> 0.16864776 | F89: =IF(F43=0,0,F88/F43-1) -> 0.14073602 | G89: =IF(G43=0,0,G88/G43-1) -> 0.26267525
A90: Uplift vs Underwriting EBITDA ($) | B90: =B88-B43 -> 63.958 | C90: =C88-C43 -> 52.871 | D90: =D88-D43 -> 63.136 | E90: =E88-E43 -> 32.363 | F90: =F88-F43 -> 27.137 | G90: =G88-G43 -> 106.0814
A92: Why it matters: covenants are tested on Credit Agreement EBITDA, so reported covenant leverage runs below real (underwriting) leverage. The gap in row 90 is how much the documents flatter the borrower.
A93: Source of definitions: Source: Fourth Amendment to A&R First Lien Credit Agreement (Sep-22-2025), Exhibit A conformed credit agreement. Exhibit A, 'Consolidated EBITDA' (PDF pp. 40–42) and 'Consolidated Net Income' (PDF pp. 44–46). The new LBO credit agreement will replace this; terms are typically similar or looser.

Sheet EBITDA_Addbacks
A1: Underwriter EBITDA – CARVE Bridge ($mm)
A2: GAAP net income → Baseline EBITDA → Underwriter EBITDA · Every add-back must pass Cash, Auditable, Recurring, Verifiable, Excluded-from-operations; gains stripped symmetrically
A4: Line | B4: FY2023 | C4: FY2024 | D4: FY2025 | E4: H1 2025 | F4: H1 2026 | G4: LTM Jun-26 | H4: % accepted | I4: Treatment
A5: STEP 1: GAAP NET INCOME → BASELINE EBITDA
A6: GAAP net income | B6: =Historicals!B17 -> 267.09 | C6: =Historicals!C17 -> 211.823 | D6: =Historicals!D17 -> 207.585 | E6: =Historicals!E17 -> 97.265 | F6: =Historicals!F17 -> 99.256 | G6: =Historicals!G17 -> 209.576
A7: + Interest expense, net | B7: =Historicals!B12 -> 51.248 | C7: =Historicals!C12 -> 49.029 | D7: =Historicals!D12 -> 54.558 | E7: =Historicals!E12 -> 27.678 | F7: =Historicals!F12 -> 27.324 | G7: =Historicals!G12 -> 54.204
A8: + Income tax expense | B8: =Historicals!B16 -> 91.652 | C8: =Historicals!C16 -> 71.776 | D8: =Historicals!D16 -> 75.315 | E8: =Historicals!E16 -> 35.152 | F8: =Historicals!F16 -> 35.734 | G8: =Historicals!G16 -> 75.897
A9: + Depreciation & amortization (total) | B9: =Historicals!B24 -> 62.2 | C9: =Historicals!C24 -> 63.498 | D9: =Historicals!D24 -> 70.69 | E9: =Historicals!E24 -> 33.326 | F9: =Historicals!F24 -> 34.037 | G9: =Historicals!G24 -> 71.401
A10: Baseline EBITDA | B10: =SUM(B6:B9) -> 472.19 | C10: =SUM(C6:C9) -> 396.126 | D10: =SUM(D6:D9) -> 408.148 | E10: =SUM(E6:E9) -> 193.421 | F10: =SUM(F6:F9) -> 196.351 | G10: =SUM(G6:G9) -> 411.078
A11: Check vs company-reported EBITDA (should be zero) | B11: =ROUND(B10-Historicals!B26,3) -> 0 | C11: =ROUND(C10-Historicals!C26,3) -> 0 | D11: =ROUND(D10-Historicals!D26,3) -> 0 | E11: =ROUND(E10-Historicals!E26,3) -> 0 | F11: =ROUND(F10-Historicals!F26,3) -> 0 | G11: =ROUND(G10-Historicals!G26,3) -> 0
A13: STEP 2: CARVE ADJUSTMENTS
A14: A1 – Strip non-operating gains (Amedisys fee; other gains in 'Other, net') | B14: =-B37-MAX(0,B40) -> -110.965 | C14: =-C37-MAX(0,C40) -> -5.208 | D14: =-D37-MAX(0,D40) -> 0 | E14: =-E37-MAX(0,E40) -> 0 | F14: =-F37-MAX(0,F40) -> -1.236 | G14: =-G37-MAX(0,G40) -> -3.05 | H14: n/a | I14: Symmetry rule: irregular gains are deducted as aggressively as losses would be added back. Mechanical – always 100%.
A15: A2 + Loss on extinguishment of debt × % accepted | B15: =Historicals!B31*$H$15 -> 0 | C15: =Historicals!C31*$H$15 -> 0 | D15: =Historicals!D31*$H$15 -> 0 | E15: =Historicals!E31*$H$15 -> 0 | F15: =Historicals!F31*$H$15 -> 0 | G15: =Historicals!G31*$H$15 -> 0 | H15: =Inputs!B25 -> 0 | I15: Non-cash and financing-related, but FAILS Recurring (FY24 $0.4mm, FY25 $4.7mm). Rejected per CARVE. Sensitivity row 59.
A16: A3 + Stock-based compensation × % accepted | B16: =Historicals!B30*$H$16 -> 0 | C16: =Historicals!C30*$H$16 -> 0 | D16: =Historicals!D30*$H$16 -> 0 | E16: =Historicals!E30*$H$16 -> 0 | F16: =Historicals!F30*$H$16 -> 0 | G16: =Historicals!G30*$H$16 -> 0 | H16: =Inputs!B23 -> 0 | I16: Non-cash, but FAILS Recurring (every year) and Excluded-from-operations (needed to retain staff). Replacement-labor rule: market pay for these people must stay in the cost base. Rejected.
A17: A4 + Restructuring, acquisition & integration (operating portion) × % accepted | B17: =(Historicals!B32+B37-B38)*$H$17 -> 0 | C17: =(Historicals!C32+C37-C38)*$H$17 -> 0 | D17: =(Historicals!D32+D37-D38)*$H$17 -> 0 | E17: =(Historicals!E32+E37-E38)*$H$17 -> 0 | F17: =(Historicals!F32+F37-F38)*$H$17 -> 0 | G17: =(Historicals!G32+G37-G38)*$H$17 -> 0 | H17: =Inputs!B24 -> 0 | I17: Cash cost every period; OPCH acquires regularly; supported only by management's schedule (no GL). FAILS C, R, V, E. Rejected.
A18: A5 + Non-operating losses: merger costs, BioScrip unclaimed-property accruals × % accepted | B18: =(B38-MIN(0,B40))*$H$18 -> 0 | C18: =(C38-MIN(0,C40))*$H$18 -> 0 | D18: =(D38-MIN(0,D40))*$H$18 -> 0 | E18: =(E38-MIN(0,E40))*$H$18 -> 0 | F18: =(F38-MIN(0,F40))*$H$18 -> 0 | G18: =(G38-MIN(0,G40))*$H$18 -> 0 | H18: 0 | I18: Cash; unclaimed-property accruals are regulatory compliance (fails Excluded-from-operations); merger costs recur with M&A strategy. Kept as cost.
A19: A6 ± JV equity earnings replaced by cash distributions received | B19: =-Historicals!B13+Historicals!B85 -> -1.53 | C19: =-Historicals!C13+Historicals!C85 -> -3.564 | D19: =-Historicals!D13+Historicals!D85 -> -3.409 | E19: =-Historicals!E13+Historicals!E85 -> -1.524 | F19: =-Historicals!F13+Historicals!F85 -> -2.293 | G19: =-Historicals!G13+Historicals!G85 -> -4.178 | H19: n/a | I19: Equity-method income is non-cash (fails Cash check). Only distributions actually received count. Mechanical – always applied.
A20: A7 + Run-rate synergies / pro forma uplift × % accepted | B20: =Historicals!B87*$H$20 -> 0 | C20: =Historicals!C87*$H$20 -> 0 | D20: =Historicals!D87*$H$20 -> 0 | E20: =Historicals!E87*$H$20 -> 0 | F20: =Historicals!F87*$H$20 -> 0 | G20: =Historicals!G87*$H$20 -> 0 | H20: 0 | I20: Speculative – not executed baseline performance. Disallowed.
A21: A8 + Repairs misclassified as opex (capitalisable) – add back, captured in capex | B21: 0 | C21: 0 | D21: 0 | E21: 0 | F21: 0 | G21: =D21+F21-E21 -> 0 | H21: n/a | I21: No repair/maintenance spikes disclosed; capex steady at 0.7–1.0% of revenue. Enter amounts here if a QoE identifies any (and raise capex %).
A22: Total CARVE adjustments | B22: =SUM(B14:B21) -> -112.495 | C22: =SUM(C14:C21) -> -8.772 | D22: =SUM(D14:D21) -> -3.409 | E22: =SUM(E14:E21) -> -1.524 | F22: =SUM(F14:F21) -> -3.529 | G22: =SUM(G14:G21) -> -7.228 | I22: LTM column uses LTM memo amounts directly (H2-25 + H1-26), so gain/loss tests apply to the LTM period itself.
A23: UNDERWRITER EBITDA | B23: =B10+B22 -> 359.695 | C23: =C10+C22 -> 387.354 | D23: =D10+D22 -> 404.739 | E23: =E10+E22 -> 191.897 | F23: =F10+F22 -> 192.822 | G23: =G10+G22 -> 403.85
A24: Underwriter EBITDA margin | B24: =IF(Historicals!B5=0,0,B23/Historicals!B5) -> 0.083604815 | C24: =IF(Historicals!C5=0,0,C23/Historicals!C5) -> 0.077498669 | D24: =IF(Historicals!D5=0,0,D23/Historicals!D5) -> 0.07164132 | E24: =IF(Historicals!E5=0,0,E23/Historicals!E5) -> 0.069804664 | F24: =IF(Historicals!F5=0,0,F23/Historicals!F5) -> 0.069036259 | G24: =IF(Historicals!G5=0,0,G23/Historicals!G5) -> 0.070931565
A25: Management Adjusted EBITDA | B25: =Historicals!B33 -> 425.183 | C25: =Historicals!C33 -> 443.789 | D25: =Historicals!D33 -> 471.284 | E25: =Historicals!E33 -> 225.784 | F25: =Historicals!F33 -> 222.252 | G25: =Historicals!G33 -> 467.752
A26: Haircut vs management ($) | B26: =B23-B25 -> -65.488 | C26: =C23-C25 -> -56.435 | D26: =D23-D25 -> -66.545 | E26: =E23-E25 -> -33.887 | F26: =F23-F25 -> -29.43 | G26: =G23-G25 -> -63.902
A27: Haircut vs management (%) | B27: =IF(B25=0,0,B26/B25) -> -0.15402309 | C27: =IF(C25=0,0,C26/C25) -> -0.12716629 | D27: =IF(D25=0,0,D26/D25) -> -0.14119936 | E27: =IF(E25=0,0,E26/E25) -> -0.15008592 | F27: =IF(F25=0,0,F26/F25) -> -0.13241726 | G27: =IF(G25=0,0,G26/G25) -> -0.13661513
A28: Check vs Historicals row 43 (should be zero) | B28: =ROUND(B23-Historicals!B43,3) -> 0 | C28: =ROUND(C23-Historicals!C43,3) -> 0 | D28: =ROUND(D23-Historicals!D43,3) -> 0 | E28: =ROUND(E23-Historicals!E43,3) -> 0 | F28: =ROUND(F23-Historicals!F43,3) -> 0 | G28: =ROUND(G23-Historicals!G43,3) -> 0
A30: STEP 3: EBITDAR (rent pivot for fixed-charge coverage)
A31: + Cash rent – operating leases | B31: 27.391 | C31: 28.505 | D31: 30.737 | E31: 15.107 | F31: 16.16 | G31: =D31+F31-E31 -> 31.79 | I31: Cash paid for operating leases (supplemental cash flow disclosure). Source: FY2025 Form 10-K (filed Feb-2026), Consolidated Financial Statements. https://www.sec.gov/Archives/edgar/data/1014739/000101473926000008/bios-20251231.htm | Source: Q2 2026 Form 10-Q (six months ended Jun-30-2026). https://www.sec.gov/Archives/edgar/data/0001014739/000101473926000023/bios-20260630.htm
A32: Underwriter EBITDAR | B32: =B23+B31 -> 387.086 | C32: =C23+C31 -> 415.859 | D32: =D23+D31 -> 435.476 | E32: =E23+E31 -> 207.004 | F32: =F23+F31 -> 208.982 | G32: =G23+G31 -> 435.64 | I32: Feeds FCCR on Credit_Stats: (EBITDAR – capex – taxes) / (debt service + rent). Rent % of revenue on Inputs!B67.
A33: Rent as % of EBITDAR | B33: =IF(B32=0,0,B31/B32) -> 0.070762053 | C33: =IF(C32=0,0,C31/C32) -> 0.068544867 | D33: =IF(D32=0,0,D31/D32) -> 0.070582535 | E33: =IF(E32=0,0,E31/E32) -> 0.072979266 | F33: =IF(F32=0,0,F31/F32) -> 0.077327234 | G33: =IF(G32=0,0,G31/G32) -> 0.072973097
A35: MEMO: COMPONENTS OF 'OTHER, NET' (non-operating line inside Baseline EBITDA)
A36: Other, net – as reported (income positive) | B36: =Historicals!B14 -> 89.865 | C36: =Historicals!C14 -> 4.831 | D36: =Historicals!D14 -> -7.857 | E36: =Historicals!E14 -> -4.927 | F36: =Historicals!F14 -> 1.236 | G36: =Historicals!G14 -> -1.694
A37: Amedisys termination fee received (gain) | B37: 106 | C37: 0 | D37: 0 | E37: 0 | F37: 0 | G37: =D37+F37-E37 -> 0 | I37: FY2025 10-K: $106.0mm Termination Fee received on behalf of Amedisys, recorded in Other, net (FY2023).
A38: Merger-related expenses (loss, shown positive) | B38: 21.1 | C38: 0 | D38: 0 | E38: 0 | F38: 0 | G38: =D38+F38-E38 -> 0 | I38: FY2025 10-K: $21.1mm merger-related expenses recorded in Other, net (FY2023).
A39: Loss on extinguishment of debt (shown positive) | B39: =Historicals!B31 -> 0 | C39: =Historicals!C31 -> 0.377 | D39: =Historicals!D31 -> 4.744 | E39: =Historicals!E31 -> 0 | F39: =Historicals!F31 -> 0 | G39: =Historicals!G31 -> 4.744
A40: Residual: BioScrip unclaimed-property accruals / reversals & other | B40: =B36-B37+B38+B39 -> 4.965 | C40: =C36-C37+C38+C39 -> 5.208 | D40: =D36-D37+D38+D39 -> -3.113 | E40: =E36-E37+E38+E39 -> -4.927 | F40: =F36-F37+F38+F39 -> 1.236 | G40: =G36-G37+G38+G39 -> 3.05 | I40: FY2025 10-K MD&A: accruals for a pre-merger BioScrip unclaimed-property voluntary disclosure program; Q2-26 10-Q: reversal of prior-year accruals. Positive = gain (stripped in A1); negative = loss (kept, A5).
A42: CARVE SCORECARD
A43: Adjustment | B43: Cash | C43: Auditable | D43: Recurring? | E43: Verifiable | F43: Excl. ops | G43: Decision | H43: % accepted | I43: Reason
A44: Amedisys termination fee (gain) | B44: Cash in | C44: Yes | D44: One-time | E44: Yes | F44: Yes | G44: STRIP GAIN | H44: =1 -> 1 | I44: Irregular gain – removed under the symmetry rule.
A45: Other non-operating gains (unclaimed-property reversals, misc.) | B45: Mixed | C45: Yes | D45: Irregular | E45: Partly | F45: Yes | G45: STRIP GAIN | H45: =1 -> 1 | I45: Irregular gains never count toward debt capacity.
A46: Loss on extinguishment of debt | B46: Non-cash ✓ | C46: Yes ✓ | D46: FY24 & FY25 ✗ | E46: Yes ✓ | F46: Yes ✓ | G46: REJECT | H46: =H15 -> 0 | I46: Fails Recurring. Note: financing write-off that cannot recur after close – the one call where the rule is arguably too strict (impact ~$4.7mm).
A47: Stock-based compensation | B47: Non-cash ✓ | C47: Yes ✓ | D47: Every year ✗ | E47: Yes ✓ | F47: No ✗ | G47: REJECT | H47: =H16 -> 0 | I47: Replacement-labor rule: employees must be paid market compensation after the buyout.
A48: Restructuring, acquisition & integration | B48: Cash ✗ | C48: Partly | D48: Every period ✗ | E48: Mgmt schedule ✗ | F48: No ✗ | G48: REJECT | H48: =H17 -> 0 | I48: Recurring cash cost of an acquisitive strategy.
A49: Merger costs; BioScrip unclaimed-property accruals | B49: Cash ✗ | C49: Yes ✓ | D49: Recurs ✗ | E49: Yes ✓ | F49: Compliance ✗ | G49: KEEP AS COST | H49: =H18 -> 0 | I49: Regulatory compliance and M&A costs are operating realities.
A50: JV equity earnings (non-cash portion) | B50: Non-cash income ✗ | C50: Yes ✓ | D50: Every year | E50: Yes ✓ | F50: n/a | G50: CASH BASIS | H50: =1 -> 1 | I50: Count only distributions received.
A51: Run-rate synergies / pro forma revenue | B51: Not realised ✗ | C51: No ✗ | D51: n/a | E51: No ✗ | F51: n/a | G51: REJECT | H51: =H20 -> 0 | I51: Speculative synergies and paper-only growth disallowed.
A52: Owner / under-market replacement labor | B52: n/a | C52: n/a | D52: n/a | E52: n/a | F52: n/a | G52: N/A | I52: Public company: executives paid market W-2 pay through SG&A; no owner salary add-back claimed. SBC handled in row 47.
A53: Capex misclassified as repairs | B53: n/a | C53: n/a | D53: n/a | E53: n/a | F53: n/a | G53: NONE FOUND | I53: No repair spikes disclosed. Row A8 left at zero.
A55: SENSITIVITY: WHAT IF REJECTED ITEMS WERE ACCEPTED? (LTM, leverage at close)
A56: Scenario | B56: Add-back | C56: EBITDA | D56: Debt / EBITDA | E56: Net debt / EBITDA
A57: Strict CARVE (base case) | B57: =0 -> 0 | C57: =$G$23+B57 -> 403.85 | D57: =IF(C57=0,0,Inputs!$B$95/C57) -> 7.7999257 | E57: =IF(C57=0,0,Cap_Stack!$B$18/C57) -> 7.6662003
A58: + Accept loss on debt extinguishment | B58: =Historicals!G31*(1-$H$15) -> 4.744 | C58: =$G$23+B58 -> 408.594 | D58: =IF(C58=0,0,Inputs!$B$95/C58) -> 7.7093643 | E58: =IF(C58=0,0,Cap_Stack!$B$18/C58) -> 7.5771915
A59: + Accept 100% of stock-based comp | B59: =Historicals!G30*(1-$H$16) -> 39.024 | C59: =$G$23+B59 -> 442.874 | D59: =IF(C59=0,0,Inputs!$B$95/C59) -> 7.1126325 | E59: =IF(C59=0,0,Cap_Stack!$B$18/C59) -> 6.9906904
A60: + Accept both | B60: =B58+B59 -> 43.768 | C60: =$G$23+B60 -> 447.618 | D60: =IF(C60=0,0,Inputs!$B$95/C60) -> 7.0372505 | E60: =IF(C60=0,0,Cap_Stack!$B$18/C60) -> 6.9166008
A61: Management Adjusted EBITDA (reference) | B61: =G25-G23 -> 63.902 | C61: =$G$23+B61 -> 467.752 | D61: =IF(C61=0,0,Inputs!$B$95/C61) -> 6.7343379 | E61: =IF(C61=0,0,Cap_Stack!$B$18/C61) -> 6.6188814
A63: LIMITATIONS
A64: • Built from public filings only (10-K, 10-Q, earnings releases). No GL, payroll or invoice detail – a quality-of-earnings report is required to validate before commitment.
A65: • 'Other, net' split relies on 10-K/10-Q MD&A disclosures; the FY2024 residual (+$5.2mm) is undisclosed and treated as a gain (stripped).
A66: • LTM tests are applied to LTM amounts (H2-2025 + H1-2026), not by netting annual tests.

Sheet Cap_Stack
A1: Pro Forma Capital Structure at Close ($mm)
A2: Structure scenario selected on Inputs!B6 · Leverage on PF LTM Jun-26 EBITDA · Rate = SOFR (Year 1) + spread
A4: Structure: | B4: =Inputs!C6 -> B: 1L + unsecured notes
A5: PF LTM Underwriting EBITDA | B5: =Historicals!G43 -> 403.85
A6: PF LTM Management Adj. EBITDA | B6: =Historicals!G33 -> 467.752
A7: Year 1 SOFR (selected path) | B7: =MAX(Inputs!C48,Inputs!B40) -> 0.035
A9: Tranche | B9: Amount | C9: Pricing | D9: All-in rate | E9: Maturity | F9: Ranking | G9: Cum. debt | H9: x Underwriting EBITDA | I9: x Mgmt EBITDA | J9: Year-1 interest
A10: Revolver ($500mm commitment, drawn) | B10: =Inputs!B79 -> 0 | C10: ="S+"&TEXT(Inputs!B38*10000,"0") -> S+300 | D10: =$B$7+Inputs!B38 -> 0.065 | E10: ~5 yr (assumed) | F10: 1st lien (pari) | G10: =B10 -> 0 | H10: =IF($B$5=0,0,G10/$B$5) -> 0 | I10: =IF($B$6=0,0,G10/$B$6) -> 0 | J10: =B10*D10+(Inputs!B14-B10)*Inputs!B39 -> 1.875
A11: First-lien term loan B | B11: =Inputs!F29 -> 2400 | C11: ="S+"&TEXT(Inputs!B35*10000,"0")&" / OID 99" -> S+325 / OID 99 | D11: =$B$7+Inputs!B35 -> 0.0675 | E11: 7 yr (assumed) | F11: 1st lien (pari) | G11: =B12 -> 2400 | H11: =IF($B$5=0,0,G11/$B$5) -> 5.9428005 | I11: =IF($B$6=0,0,G11/$B$6) -> 5.1309241 | J11: =B11*D11 -> 162
A12: Total first-lien debt | B12: =B10+B11 -> 2400 | G12: =B12 -> 2400 | H12: =IF($B$5=0,0,G12/$B$5) -> 5.9428005 | I12: =IF($B$6=0,0,G12/$B$6) -> 5.1309241 | J12: =J10+J11 -> 163.875
A13: Second-lien term loan | B13: =Inputs!F30 -> 0 | C13: ="S+"&TEXT(Inputs!B36*10000,"0") -> S+600 | D13: =$B$7+Inputs!B36 -> 0.095 | E13: 8 yr (assumed) | F13: 2nd lien | G13: =B14 -> 2400 | H13: =IF($B$5=0,0,G13/$B$5) -> 5.9428005 | I13: =IF($B$6=0,0,G13/$B$6) -> 5.1309241 | J13: =B13*D13 -> 0
A14: Total secured debt | B14: =B12+B13 -> 2400 | G14: =B14 -> 2400 | H14: =IF($B$5=0,0,G14/$B$5) -> 5.9428005 | I14: =IF($B$6=0,0,G14/$B$6) -> 5.1309241 | J14: =J12+J13 -> 163.875
A15: Senior unsecured notes | B15: =Inputs!F31 -> 750 | C15: =TEXT(Inputs!B37,"0.00%")&" fixed" -> 7.50% fixed | D15: =Inputs!B37 -> 0.075 | E15: 8 yr (assumed) | F15: Unsecured | G15: =B16 -> 3150 | H15: =IF($B$5=0,0,G15/$B$5) -> 7.7999257 | I15: =IF($B$6=0,0,G15/$B$6) -> 6.7343379 | J15: =B15*D15 -> 56.25
A16: Total debt | B16: =B14+B15 -> 3150 | G16: =B16 -> 3150 | H16: =IF($B$5=0,0,G16/$B$5) -> 7.7999257 | I16: =IF($B$6=0,0,G16/$B$6) -> 6.7343379 | J16: =J14+J15 -> 220.125
A17: Less: cash at close | B17: =Inputs!F81 -> 54.005
A18: Net debt | B18: =B16-B17 -> 3095.995 | H18: =IF($B$5=0,0,B18/$B$5) -> 7.6662003 | I18: =IF($B$6=0,0,B18/$B$6) -> 6.6188814
A19: Sponsor + McKesson equity | B19: =Inputs!B80 -> 2873.3
A20: Total capitalization | B20: =B16+B19 -> 6023.3
A21: Equity cushion beneath all debt | B21: =IF(B20=0,0,B19/B20) -> 0.47703086
A22: Value cushion beneath first lien (1 – 1L debt / total cap) | B22: =IF(B20=0,0,1-B12/B20) -> 0.60154732
A23: Year-1 interest coverage (Underwriting EBITDA / interest) | B23: =IF(J16=0,0,B5/J16) -> 1.8346394
A24: Weighted average cost of debt | B24: =IF(B16=0,0,J16/B16) -> 0.069880952
A25: Total debt / Credit Agreement EBITDA (as reported to lenders) | B25: =IF(Historicals!G88=0,0,B16/Historicals!G88) -> 6.1773015
A26: Pre-deal vs pro forma | B26: Pre-deal (Jun-26) | C26: Pro forma | D26: Change
A27: Total debt | B27: =Historicals!F69 -> 1172.915 | C27: =B16 -> 3150 | D27: =C27-B27 -> 1977.085
A28: Net debt | B28: =Historicals!F70 -> 979.148 | C28: =B18 -> 3095.995 | D28: =C28-B28 -> 2116.847
A29: Total debt / Underwriting EBITDA | B29: =Historicals!G74 -> 2.9043333 | C29: =H16 -> 7.7999257 | D29: =C29-B29 -> 4.8955924
A30: Net debt / Underwriting EBITDA | B30: =Historicals!G75 -> 2.4245339 | C30: =H18 -> 7.6662003 | D30: =C30-B30 -> 5.2416665
A31: Annual interest expense | B31: =Historicals!G12 -> 54.204 | C31: =J16 -> 220.125 | D31: =C31-B31 -> 165.921
A32: Interest coverage (Underwriting EBITDA / interest) | B32: =Historicals!G76 -> 7.4505572 | C32: =B23 -> 1.8346394 | D32: =C32-B32 -> -5.6159177
A34: Pre-deal: 1L TLB $672.9mm at SOFR+175 (5.37%, due Sep-2032) + $500mm 4.375% notes (due Oct-2029); both repaid at close. Source: Q2 2026 Form 10-Q (six months ended Jun-30-2026). https://www.sec.gov/Archives/edgar/data/0001014739/000101473926000023/bios-20260630.htm

Sheet Projections
A1: Projections & Debt Schedule ($mm)
A2: Year 0 = pro forma close on LTM Jun-26 · Interest on beginning balances (no circularity) · Case, structure and SOFR set on Inputs
A3: Case: | B3: =Inputs!C5 -> Lender Base | D3: Structure: | E3: =Inputs!C6 -> B: 1L + unsecured notes | H3: Rates: | I3: =Inputs!C7 -> Base SOFR
B4: PF Close | C4: 2027 | D4: 2028 | E4: 2029 | F4: 2030 | G4: 2031 | H4: 2032 | I4: 2033
A5: Year # | B5: 0 | C5: =B5+1 -> 1 | D5: =C5+1 -> 2 | E5: =D5+1 -> 3 | F5: =E5+1 -> 4 | G5: =F5+1 -> 5 | H5: =G5+1 -> 6 | I5: =H5+1 -> 7
A6: OPERATING BUILD
A7: Net revenue | B7: =Historicals!G5 -> 5693.516 | C7: =B7*(1+C8) -> 5978.1918 | D7: =C7*(1+D8) -> 6277.1014 | E7: =D7*(1+E8) -> 6559.571 | F7: =E7*(1+F8) -> 6854.7516 | G7: =F7*(1+G8) -> 7128.9417 | H7: =G7*(1+H8) -> 7414.0994 | I7: =H7*(1+I8) -> 7710.6634
A8: Growth | C8: =Inputs!C55 -> 0.05 | D8: =Inputs!D55 -> 0.05 | E8: =Inputs!E55 -> 0.045 | F8: =Inputs!F55 -> 0.045 | G8: =Inputs!G55 -> 0.04 | H8: =Inputs!H55 -> 0.04 | I8: =Inputs!I55 -> 0.04
A9: Underwriting EBITDA margin | B9: =Historicals!G44 -> 0.070931565 | C9: =$B$9+Inputs!C60 -> 0.070931565 | D9: =$B$9+Inputs!D60 -> 0.070931565 | E9: =$B$9+Inputs!E60 -> 0.070931565 | F9: =$B$9+Inputs!F60 -> 0.070931565 | G9: =$B$9+Inputs!G60 -> 0.070931565 | H9: =$B$9+Inputs!H60 -> 0.070931565 | I9: =$B$9+Inputs!I60 -> 0.070931565
A10: Underwriting EBITDA | B10: =Historicals!G43 -> 403.85 | C10: =C7*C9 -> 424.0425 | D10: =D7*D9 -> 445.24462 | E10: =E7*E9 -> 465.28063 | F10: =F7*F9 -> 486.21826 | G10: =G7*G9 -> 505.66699 | H10: =H7*H9 -> 525.89367 | I10: =I7*I9 -> 546.92942
A11: Capex | C11: =C7*Inputs!$B$63 -> 44.836438 | D11: =D7*Inputs!$B$63 -> 47.07826 | E11: =E7*Inputs!$B$63 -> 49.196782 | F11: =F7*Inputs!$B$63 -> 51.410637 | G11: =G7*Inputs!$B$63 -> 53.467063 | H11: =H7*Inputs!$B$63 -> 55.605745 | I11: =I7*Inputs!$B$63 -> 57.829975
A12: D&A (tax) | C12: =C7*Inputs!$B$64 -> 74.727397 | D12: =D7*Inputs!$B$64 -> 78.463767 | E12: =E7*Inputs!$B$64 -> 81.994637 | F12: =F7*Inputs!$B$64 -> 85.684396 | G12: =G7*Inputs!$B$64 -> 89.111771 | H12: =H7*Inputs!$B$64 -> 92.676242 | I12: =I7*Inputs!$B$64 -> 96.383292
A13: Increase in net working capital | C13: =(C7-B7)*Inputs!$B$65 -> 15.372493 | D13: =(D7-C7)*Inputs!$B$65 -> 16.141118 | E13: =(E7-D7)*Inputs!$B$65 -> 15.253356 | F13: =(F7-E7)*Inputs!$B$65 -> 15.939757 | G13: =(G7-F7)*Inputs!$B$65 -> 14.806264 | H13: =(H7-G7)*Inputs!$B$65 -> 15.398514 | I13: =(I7-H7)*Inputs!$B$65 -> 16.014455
A14: Credit Agreement EBITDA (covenant basis) | B14: =Historicals!G88 -> 509.9314 | C14: =C10*(1+Historicals!$G$89) -> 535.42797 | D14: =D10*(1+Historicals!$G$89) -> 562.19937 | E14: =E10*(1+Historicals!$G$89) -> 587.49834 | F14: =F10*(1+Historicals!$G$89) -> 613.93577 | G14: =G10*(1+Historicals!$G$89) -> 638.4932 | H14: =H10*(1+Historicals!$G$89) -> 664.03292 | I14: =I10*(1+Historicals!$G$89) -> 690.59424
A15: RATES
A16: SOFR (selected path) | C16: =Inputs!C48 -> 0.035 | D16: =Inputs!D48 -> 0.0325 | E16: =Inputs!E48 -> 0.0325 | F16: =Inputs!F48 -> 0.0325 | G16: =Inputs!G48 -> 0.0325 | H16: =Inputs!H48 -> 0.0325 | I16: =Inputs!I48 -> 0.0325
A17: Reference rate after floor | C17: =MAX(C16,Inputs!$B$40) -> 0.035 | D17: =MAX(D16,Inputs!$B$40) -> 0.0325 | E17: =MAX(E16,Inputs!$B$40) -> 0.0325 | F17: =MAX(F16,Inputs!$B$40) -> 0.0325 | G17: =MAX(G16,Inputs!$B$40) -> 0.0325 | H17: =MAX(H16,Inputs!$B$40) -> 0.0325 | I17: =MAX(I16,Inputs!$B$40) -> 0.0325
A19: INTEREST (on beginning balances)
A20: Revolver interest + undrawn fee | C20: =C36*(C17+Inputs!$B$38)+(Inputs!$B$14-C36)*Inputs!$B$39 -> 1.875 | D20: =D36*(D17+Inputs!$B$38)+(Inputs!$B$14-D36)*Inputs!$B$39 -> 1.875 | E20: =E36*(E17+Inputs!$B$38)+(Inputs!$B$14-E36)*Inputs!$B$39 -> 1.875 | F20: =F36*(F17+Inputs!$B$38)+(Inputs!$B$14-F36)*Inputs!$B$39 -> 1.875 | G20: =G36*(G17+Inputs!$B$38)+(Inputs!$B$14-G36)*Inputs!$B$39 -> 1.875 | H20: =H36*(H17+Inputs!$B$38)+(Inputs!$B$14-H36)*Inputs!$B$39 -> 1.875 | I20: =I36*(I17+Inputs!$B$38)+(Inputs!$B$14-I36)*Inputs!$B$39 -> 1.875
A21: First-lien TLB interest | C21: =C40*(C17+Inputs!$B$35) -> 162 | D21: =D40*(D17+Inputs!$B$35) -> 152.35405 | E21: =E40*(E17+Inputs!$B$35) -> 147.89361 | F21: =F40*(F17+Inputs!$B$35) -> 142.7623 | G21: =G40*(G17+Inputs!$B$35) -> 136.96712 | H21: =H40*(H17+Inputs!$B$35) -> 130.46426 | I21: =I40*(I17+Inputs!$B$35) -> 123.26753
A22: Second-lien TL interest | C22: =C45*(C17+Inputs!$B$36) -> 0 | D22: =D45*(D17+Inputs!$B$36) -> 0 | E22: =E45*(E17+Inputs!$B$36) -> 0 | F22: =F45*(F17+Inputs!$B$36) -> 0 | G22: =G45*(G17+Inputs!$B$36) -> 0 | H22: =H45*(H17+Inputs!$B$36) -> 0 | I22: =I45*(I17+Inputs!$B$36) -> 0
A23: Senior unsecured notes interest | C23: =C47*Inputs!$B$37 -> 56.25 | D23: =D47*Inputs!$B$37 -> 56.25 | E23: =E47*Inputs!$B$37 -> 56.25 | F23: =F47*Inputs!$B$37 -> 56.25 | G23: =G47*Inputs!$B$37 -> 56.25 | H23: =H47*Inputs!$B$37 -> 56.25 | I23: =I47*Inputs!$B$37 -> 56.25
A24: Total cash interest | C24: =SUM(C20:C23) -> 220.125 | D24: =SUM(D20:D23) -> 210.47905 | E24: =SUM(E20:E23) -> 206.01861 | F24: =SUM(F20:F23) -> 200.8873 | G24: =SUM(G20:G23) -> 195.09212 | H24: =SUM(H20:H23) -> 188.58926 | I24: =SUM(I20:I23) -> 181.39253
A26: FREE CASH FLOW
A27: Underwriting EBITDA | C27: =C10 -> 424.0425 | D27: =D10 -> 445.24462 | E27: =E10 -> 465.28063 | F27: =F10 -> 486.21826 | G27: =G10 -> 505.66699 | H27: =H10 -> 525.89367 | I27: =I10 -> 546.92942
A28: – Cash interest | C28: =-C24 -> -220.125 | D28: =-D24 -> -210.47905 | E28: =-E24 -> -206.01861 | F28: =-F24 -> -200.8873 | G28: =-G24 -> -195.09212 | H28: =-H24 -> -188.58926 | I28: =-I24 -> -181.39253
A29: – Cash taxes (interest deduction capped at 30% of EBITDA) | C29: =-MAX(0,C10-C12-MIN(C24,C10*Inputs!$D$66))*Inputs!$B$66 -> -55.525588 | D29: =-MAX(0,D10-D12-MIN(D24,D10*Inputs!$D$66))*Inputs!$B$66 -> -58.301868 | E29: =-MAX(0,E10-E12-MIN(E24,E10*Inputs!$D$66))*Inputs!$B$66 -> -60.925452 | F29: =-MAX(0,F10-F12-MIN(F24,F10*Inputs!$D$66))*Inputs!$B$66 -> -63.667097 | G29: =-MAX(0,G10-G12-MIN(G24,G10*Inputs!$D$66))*Inputs!$B$66 -> -66.213781 | H29: =-MAX(0,H10-H12-MIN(H24,H10*Inputs!$D$66))*Inputs!$B$66 -> -68.862332 | I29: =-MAX(0,I10-I12-MIN(I24,I10*Inputs!$D$66))*Inputs!$B$66 -> -71.616825
A30: – Capex | C30: =-C11 -> -44.836438 | D30: =-D11 -> -47.07826 | E30: =-E11 -> -49.196782 | F30: =-F11 -> -51.410637 | G30: =-G11 -> -53.467063 | H30: =-H11 -> -55.605745 | I30: =-I11 -> -57.829975
A31: – Increase in NWC | C31: =-C13 -> -15.372493 | D31: =-D13 -> -16.141118 | E31: =-E13 -> -15.253356 | F31: =-F13 -> -15.939757 | G31: =-G13 -> -14.806264 | H31: =-H13 -> -15.398514 | I31: =-I13 -> -16.014455
A32: Free cash flow before debt repayment | C32: =SUM(C27:C31) -> 88.18298 | D32: =SUM(D27:D31) -> 113.24433 | E32: =SUM(E27:E31) -> 133.88643 | F32: =SUM(F27:F31) -> 154.31347 | G32: =SUM(G27:G31) -> 176.08777 | H32: =SUM(H27:H31) -> 197.43782 | I32: =SUM(I27:I31) -> 220.07563
A33: – Mandatory 1L amortization | C33: =-C41 -> -24 | D33: =-D41 -> -24 | E33: =-E41 -> -24 | F33: =-F41 -> -24 | G33: =-G41 -> -24 | H33: =-H41 -> -24 | I33: =-I41 -> -24
A34: FCF after mandatory debt service | C34: =C32+C33 -> 64.18298 | D34: =D32+D33 -> 89.244326 | E34: =E32+E33 -> 109.88643 | F34: =F32+F33 -> 130.31347 | G34: =G32+G33 -> 152.08777 | H34: =H32+H33 -> 173.43782 | I34: =I32+I33 -> 196.07563
A35: DEBT SCHEDULE
A36: Revolver – beginning | C36: =B38 -> 0 | D36: =C38 -> 0 | E36: =D38 -> 0 | F36: =E38 -> 0 | G36: =F38 -> 0 | H36: =G38 -> 0 | I36: =H38 -> 0
A37: Revolver – draw / (repayment) | C37: =IF(C52<0,MIN(-C52,Inputs!$B$14-C36),-MIN(C36,C52)) -> 0 | D37: =IF(D52<0,MIN(-D52,Inputs!$B$14-D36),-MIN(D36,D52)) -> 0 | E37: =IF(E52<0,MIN(-E52,Inputs!$B$14-E36),-MIN(E36,E52)) -> 0 | F37: =IF(F52<0,MIN(-F52,Inputs!$B$14-F36),-MIN(F36,F52)) -> 0 | G37: =IF(G52<0,MIN(-G52,Inputs!$B$14-G36),-MIN(G36,G52)) -> 0 | H37: =IF(H52<0,MIN(-H52,Inputs!$B$14-H36),-MIN(H36,H52)) -> 0 | I37: =IF(I52<0,MIN(-I52,Inputs!$B$14-I36),-MIN(I36,I52)) -> 0
A38: Revolver – ending | B38: =Cap_Stack!B10 -> 0 | C38: =C36+C37 -> 0 | D38: =D36+D37 -> 0 | E38: =E36+E37 -> 0 | F38: =F36+F37 -> 0 | G38: =G36+G37 -> 0 | H38: =H36+H37 -> 0 | I38: =I36+I37 -> 0
A40: 1L TLB – beginning | C40: =B43 -> 2400 | D40: =C43 -> 2343.9085 | E40: =D43 -> 2275.2863 | F40: =E43 -> 2196.3431 | G40: =F43 -> 2107.1864 | H40: =G43 -> 2007.1425 | I40: =H43 -> 1896.4236
A41: 1L TLB – mandatory amortization | C41: =MIN(C40,Inputs!$B$41*Inputs!$F$29) -> 24 | D41: =MIN(D40,Inputs!$B$41*Inputs!$F$29) -> 24 | E41: =MIN(E40,Inputs!$B$41*Inputs!$F$29) -> 24 | F41: =MIN(F40,Inputs!$B$41*Inputs!$F$29) -> 24 | G41: =MIN(G40,Inputs!$B$41*Inputs!$F$29) -> 24 | H41: =MIN(H40,Inputs!$B$41*Inputs!$F$29) -> 24 | I41: =MIN(I40,Inputs!$B$41*Inputs!$F$29) -> 24
A42: 1L TLB – excess cash flow sweep (50% of the year's excess cash flow) | C42: =MIN(C40-C41,MAX(0,MIN(C34+C37,C53-Inputs!$B$17))*Inputs!$B$42) -> 32.09149 | D42: =MIN(D40-D41,MAX(0,MIN(D34+D37,D53-Inputs!$B$17))*Inputs!$B$42) -> 44.622163 | E42: =MIN(E40-E41,MAX(0,MIN(E34+E37,E53-Inputs!$B$17))*Inputs!$B$42) -> 54.943215 | F42: =MIN(F40-F41,MAX(0,MIN(F34+F37,F53-Inputs!$B$17))*Inputs!$B$42) -> 65.156733 | G42: =MIN(G40-G41,MAX(0,MIN(G34+G37,G53-Inputs!$B$17))*Inputs!$B$42) -> 76.043885 | H42: =MIN(H40-H41,MAX(0,MIN(H34+H37,H53-Inputs!$B$17))*Inputs!$B$42) -> 86.718908 | I42: =MIN(I40-I41,MAX(0,MIN(I34+I37,I53-Inputs!$B$17))*Inputs!$B$42) -> 98.037815
A43: 1L TLB – ending | B43: =Cap_Stack!B11 -> 2400 | C43: =C40-C41-C42 -> 2343.9085 | D43: =D40-D41-D42 -> 2275.2863 | E43: =E40-E41-E42 -> 2196.3431 | F43: =F40-F41-F42 -> 2107.1864 | G43: =G40-G41-G42 -> 2007.1425 | H43: =H40-H41-H42 -> 1896.4236 | I43: =I40-I41-I42 -> 1774.3858
A45: 2L TL – beginning (bullet) | C45: =B46 -> 0 | D45: =C46 -> 0 | E45: =D46 -> 0 | F45: =E46 -> 0 | G45: =F46 -> 0 | H45: =G46 -> 0 | I45: =H46 -> 0
A46: 2L TL – ending | B46: =Cap_Stack!B13 -> 0 | C46: =C45 -> 0 | D46: =D45 -> 0 | E46: =E45 -> 0 | F46: =F45 -> 0 | G46: =G45 -> 0 | H46: =H45 -> 0 | I46: =I45 -> 0
A47: Senior notes – beginning (bullet) | C47: =B48 -> 750 | D47: =C48 -> 750 | E47: =D48 -> 750 | F47: =E48 -> 750 | G47: =F48 -> 750 | H47: =G48 -> 750 | I47: =H48 -> 750
A48: Senior notes – ending | B48: =Cap_Stack!B15 -> 750 | C48: =C47 -> 750 | D48: =D47 -> 750 | E48: =E47 -> 750 | F48: =F47 -> 750 | G48: =G47 -> 750 | H48: =H47 -> 750 | I48: =I47 -> 750
A50: CASH
A51: Cash – beginning | C51: =B55 -> 54.005 | D51: =C55 -> 86.09649 | E51: =D55 -> 130.71865 | F51: =E55 -> 185.66187 | G51: =F55 -> 250.8186 | H51: =G55 -> 326.86249 | I51: =H55 -> 413.58139
A52: Cash available above minimum before revolver | C52: =C51+C34-Inputs!$B$17 -> 68.18798 | D52: =D51+D34-Inputs!$B$17 -> 125.34082 | E52: =E51+E34-Inputs!$B$17 -> 190.60508 | F52: =F51+F34-Inputs!$B$17 -> 265.97533 | G52: =G51+G34-Inputs!$B$17 -> 352.90637 | H52: =H51+H34-Inputs!$B$17 -> 450.3003 | I52: =I51+I34-Inputs!$B$17 -> 559.65702
A53: Cash after revolver activity | C53: =C51+C34+C37 -> 118.18798 | D53: =D51+D34+D37 -> 175.34082 | E53: =E51+E34+E37 -> 240.60508 | F53: =F51+F34+F37 -> 315.97533 | G53: =G51+G34+G37 -> 402.90637 | H53: =H51+H34+H37 -> 500.3003 | I53: =I51+I34+I37 -> 609.65702
A54: Excess cash above minimum | C54: =MAX(0,C53-Inputs!$B$17) -> 68.18798 | D54: =MAX(0,D53-Inputs!$B$17) -> 125.34082 | E54: =MAX(0,E53-Inputs!$B$17) -> 190.60508 | F54: =MAX(0,F53-Inputs!$B$17) -> 265.97533 | G54: =MAX(0,G53-Inputs!$B$17) -> 352.90637 | H54: =MAX(0,H53-Inputs!$B$17) -> 450.3003 | I54: =MAX(0,I53-Inputs!$B$17) -> 559.65702
A55: Cash – ending | B55: =Cap_Stack!B17 -> 54.005 | C55: =C53-C42 -> 86.09649 | D55: =D53-D42 -> 130.71865 | E55: =E53-E42 -> 185.66187 | F55: =F53-F42 -> 250.8186 | G55: =G53-G42 -> 326.86249 | H55: =H53-H42 -> 413.58139 | I55: =I53-I42 -> 511.61921
A57: SUMMARY
A58: Total debt – ending | B58: =B38+B43+B46+B48 -> 3150 | C58: =C38+C43+C46+C48 -> 3093.9085 | D58: =D38+D43+D46+D48 -> 3025.2863 | E58: =E38+E43+E46+E48 -> 2946.3431 | F58: =F38+F43+F46+F48 -> 2857.1864 | G58: =G38+G43+G46+G48 -> 2757.1425 | H58: =H38+H43+H46+H48 -> 2646.4236 | I58: =I38+I43+I46+I48 -> 2524.3858
A59: First-lien debt – ending (revolver + TLB) | B59: =B38+B43 -> 2400 | C59: =C38+C43 -> 2343.9085 | D59: =D38+D43 -> 2275.2863 | E59: =E38+E43 -> 2196.3431 | F59: =F38+F43 -> 2107.1864 | G59: =G38+G43 -> 2007.1425 | H59: =H38+H43 -> 1896.4236 | I59: =I38+I43 -> 1774.3858
A60: Net debt – ending | B60: =B58-B55 -> 3095.995 | C60: =C58-C55 -> 3007.812 | D60: =D58-D55 -> 2894.5677 | E60: =E58-E55 -> 2760.6813 | F60: =F58-F55 -> 2606.3678 | G60: =G58-G55 -> 2430.28 | H60: =H58-H55 -> 2232.8422 | I60: =I58-I55 -> 2012.7666
A61: Liquidity (cash + undrawn revolver) | B61: =B55+Inputs!$B$14-B38 -> 554.005 | C61: =C55+Inputs!$B$14-C38 -> 586.09649 | D61: =D55+Inputs!$B$14-D38 -> 630.71865 | E61: =E55+Inputs!$B$14-E38 -> 685.66187 | F61: =F55+Inputs!$B$14-F38 -> 750.8186 | G61: =G55+Inputs!$B$14-G38 -> 826.86249 | H61: =H55+Inputs!$B$14-H38 -> 913.58139 | I61: =I55+Inputs!$B$14-I38 -> 1011.6192
A62: Funding shortfall – cash below zero (= default) | B62: =MAX(0,-B55) -> 0 | C62: =MAX(0,-C55) -> 0 | D62: =MAX(0,-D55) -> 0 | E62: =MAX(0,-E55) -> 0 | F62: =MAX(0,-F55) -> 0 | G62: =MAX(0,-G55) -> 0 | H62: =MAX(0,-H55) -> 0 | I62: =MAX(0,-I55) -> 0

Sheet Credit_Stats
A1: Credit Statistics, Covenant Headroom & Distress Flags
A2: Flags: 1 = trigger hit · Triggers set on Inputs rows 69–72 · Run all three cases (Inputs!B5) and compare
A3: Case: | B3: =Inputs!C5 -> Lender Base | D3: Structure: | E3: =Inputs!C6 -> B: 1L + unsecured notes | H3: Rates: | I3: =Inputs!C7 -> Base SOFR
A4: Metric | B4: PF Close | C4: 2027 | D4: 2028 | E4: 2029 | F4: 2030 | G4: 2031 | H4: 2032 | I4: 2033
A5: Underwriting EBITDA | B5: =Projections!B10 -> 403.85 | C5: =Projections!C10 -> 424.0425 | D5: =Projections!D10 -> 445.24462 | E5: =Projections!E10 -> 465.28063 | F5: =Projections!F10 -> 486.21826 | G5: =Projections!G10 -> 505.66699 | H5: =Projections!H10 -> 525.89367 | I5: =Projections!I10 -> 546.92942
A6: Total debt | B6: =Projections!B58 -> 3150 | C6: =Projections!C58 -> 3093.9085 | D6: =Projections!D58 -> 3025.2863 | E6: =Projections!E58 -> 2946.3431 | F6: =Projections!F58 -> 2857.1864 | G6: =Projections!G58 -> 2757.1425 | H6: =Projections!H58 -> 2646.4236 | I6: =Projections!I58 -> 2524.3858
A7: Net debt | B7: =Projections!B60 -> 3095.995 | C7: =Projections!C60 -> 3007.812 | D7: =Projections!D60 -> 2894.5677 | E7: =Projections!E60 -> 2760.6813 | F7: =Projections!F60 -> 2606.3678 | G7: =Projections!G60 -> 2430.28 | H7: =Projections!H60 -> 2232.8422 | I7: =Projections!I60 -> 2012.7666
A8: First-lien debt | B8: =Projections!B59 -> 2400 | C8: =Projections!C59 -> 2343.9085 | D8: =Projections!D59 -> 2275.2863 | E8: =Projections!E59 -> 2196.3431 | F8: =Projections!F59 -> 2107.1864 | G8: =Projections!G59 -> 2007.1425 | H8: =Projections!H59 -> 1896.4236 | I8: =Projections!I59 -> 1774.3858
A9: Credit Agreement EBITDA (covenant basis) | B9: =Projections!B14 -> 509.9314 | C9: =Projections!C14 -> 535.42797 | D9: =Projections!D14 -> 562.19937 | E9: =Projections!E14 -> 587.49834 | F9: =Projections!F14 -> 613.93577 | G9: =Projections!G14 -> 638.4932 | H9: =Projections!H14 -> 664.03292 | I9: =Projections!I14 -> 690.59424
A10: LEVERAGE (underwriting basis unless noted)
A11: Total gross leverage | B11: =IF(B5<=0,99,B6/B5) -> 7.7999257 | C11: =IF(C5<=0,99,C6/C5) -> 7.2962227 | D11: =IF(D5<=0,99,D6/D5) -> 6.7946611 | E11: =IF(E5<=0,99,E6/E5) -> 6.3324001 | F11: =IF(F5<=0,99,F6/F5) -> 5.8763453 | G11: =IF(G5<=0,99,G6/G5) -> 5.4524866 | H11: =IF(H5<=0,99,H6/H5) -> 5.0322408 | I11: =IF(I5<=0,99,I6/I5) -> 4.6155604
A12: Total net leverage | B12: =IF(B5<=0,99,B7/B5) -> 7.6662003 | C12: =IF(C5<=0,99,C7/C5) -> 7.0931853 | D12: =IF(D5<=0,99,D7/D5) -> 6.5010727 | E12: =IF(E5<=0,99,E7/E5) -> 5.9333681 | F12: =IF(F5<=0,99,F7/F5) -> 5.3604893 | G12: =IF(G5<=0,99,G7/G5) -> 4.8060879 | H12: =IF(H5<=0,99,H7/H5) -> 4.2458054 | I12: =IF(I5<=0,99,I7/I5) -> 3.6801213
A13: First-lien net leverage | B13: =IF(B5<=0,99,(B8-Projections!B55)/B5) -> 5.8090752 | C13: =IF(C5<=0,99,(C8-Projections!C55)/C5) -> 5.3244946 | D13: =IF(D5<=0,99,(D8-Projections!D55)/D5) -> 4.8166055 | E13: =IF(E5<=0,99,(E8-Projections!E55)/E5) -> 4.3214377 | F13: =IF(F5<=0,99,(F8-Projections!F55)/F5) -> 3.8179722 | G13: =IF(G5<=0,99,(G8-Projections!G55)/G5) -> 3.3228984 | H13: =IF(H5<=0,99,(H8-Projections!H55)/H5) -> 2.8196616 | I13: =IF(I5<=0,99,(I8-Projections!I55)/I5) -> 2.3088291
A14: Total net leverage – Credit Agreement basis (as reported) | B14: =IF(B9<=0,99,B7/B9) -> 6.0713951 | C14: =IF(C9<=0,99,C7/C9) -> 5.6175848 | D14: =IF(D9<=0,99,D7/D9) -> 5.1486498 | E14: =IF(E9<=0,99,E7/E9) -> 4.6990452 | F14: =IF(F9<=0,99,F7/F9) -> 4.2453428 | G14: =IF(G9<=0,99,G7/G9) -> 3.806274 | H14: =IF(H9<=0,99,H7/H9) -> 3.3625474 | I14: =IF(I9<=0,99,I7/I9) -> 2.914543
A15: COVERAGE & CASH FLOW
A16: Interest coverage (EBITDA / cash interest) | C16: =IF(Projections!C24=0,0,C5/Projections!C24) -> 1.9263714 | D16: =IF(Projections!D24=0,0,D5/Projections!D24) -> 2.1153869 | E16: =IF(Projections!E24=0,0,E5/Projections!E24) -> 2.2584398 | F16: =IF(Projections!F24=0,0,F5/Projections!F24) -> 2.4203534 | G16: =IF(Projections!G24=0,0,G5/Projections!G24) -> 2.5919397 | H16: =IF(Projections!H24=0,0,H5/Projections!H24) -> 2.7885663 | I16: =IF(Projections!I24=0,0,I5/Projections!I24) -> 3.0151705
A17: FCCR – EBITDAR basis: (EBITDAR – capex – taxes) / (debt service + rent) | C17: =IF((Projections!C24+Projections!C41+Projections!C7*Inputs!$B$67)=0,0,(C5+Projections!C7*Inputs!$B$67-Projections!C11+Projections!C29)/(Projections!C24+Projections!C41+Projections!C7*Inputs!$B$67)) -> 1.2878198 | D17: =IF((Projections!D24+Projections!D41+Projections!D7*Inputs!$B$67)=0,0,(D5+Projections!D7*Inputs!$B$67-Projections!D11+Projections!D29)/(Projections!D24+Projections!D41+Projections!D7*Inputs!$B$67)) -> 1.3926792 | E17: =IF((Projections!E24+Projections!E41+Projections!E7*Inputs!$B$67)=0,0,(E5+Projections!E7*Inputs!$B$67-Projections!E11+Projections!E29)/(Projections!E24+Projections!E41+Projections!E7*Inputs!$B$67)) -> 1.4714423 | F17: =IF((Projections!F24+Projections!F41+Projections!F7*Inputs!$B$67)=0,0,(F5+Projections!F7*Inputs!$B$67-Projections!F11+Projections!F29)/(Projections!F24+Projections!F41+Projections!F7*Inputs!$B$67)) -> 1.5584252 | G17: =IF((Projections!G24+Projections!G41+Projections!G7*Inputs!$B$67)=0,0,(G5+Projections!G7*Inputs!$B$67-Projections!G11+Projections!G29)/(Projections!G24+Projections!G41+Projections!G7*Inputs!$B$67)) -> 1.6479097 | H17: =IF((Projections!H24+Projections!H41+Projections!H7*Inputs!$B$67)=0,0,(H5+Projections!H7*Inputs!$B$67-Projections!H11+Projections!H29)/(Projections!H24+Projections!H41+Projections!H7*Inputs!$B$67)) -> 1.7474954 | I17: =IF((Projections!I24+Projections!I41+Projections!I7*Inputs!$B$67)=0,0,(I5+Projections!I7*Inputs!$B$67-Projections!I11+Projections!I29)/(Projections!I24+Projections!I41+Projections!I7*Inputs!$B$67)) -> 1.8585596
A18: FCF before debt repayment / total debt | C18: =IF(C6=0,0,Projections!C32/C6) -> 0.028502129 | D18: =IF(D6=0,0,Projections!D32/D6) -> 0.037432597 | E18: =IF(E6=0,0,Projections!E32/E6) -> 0.045441561 | F18: =IF(F6=0,0,Projections!F32/F6) -> 0.05400889 | G18: =IF(G6=0,0,Projections!G32/G6) -> 0.063866038 | H18: =IF(H6=0,0,Projections!H32/H6) -> 0.074605523 | I18: =IF(I6=0,0,Projections!I32/I6) -> 0.087179872
A19: Cumulative debt paydown (% of close) | C19: =IF($B$6=0,0,1-C6/$B$6) -> 0.017806822 | D19: =IF($B$6=0,0,1-D6/$B$6) -> 0.039591636 | E19: =IF($B$6=0,0,1-E6/$B$6) -> 0.064652974 | F19: =IF($B$6=0,0,1-F6/$B$6) -> 0.092956699 | G19: =IF($B$6=0,0,1-G6/$B$6) -> 0.12471666 | H19: =IF($B$6=0,0,1-H6/$B$6) -> 0.15986552 | I19: =IF($B$6=0,0,1-I6/$B$6) -> 0.19860769
A20: Liquidity (cash + undrawn revolver) | B20: =Projections!B61 -> 554.005 | C20: =Projections!C61 -> 586.09649 | D20: =Projections!D61 -> 630.71865 | E20: =Projections!E61 -> 685.66187 | F20: =Projections!F61 -> 750.8186 | G20: =Projections!G61 -> 826.86249 | H20: =Projections!H61 -> 913.58139 | I20: =Projections!I61 -> 1011.6192
A22: COVENANT HEADROOM (tested on Credit Agreement EBITDA – assumed new-deal covenant)
A23: Covenant: max first-lien net leverage | B23: =Inputs!$B$69 -> 7 | C23: =Inputs!$B$69 -> 7 | D23: =Inputs!$B$69 -> 7 | E23: =Inputs!$B$69 -> 7 | F23: =Inputs!$B$69 -> 7 | G23: =Inputs!$B$69 -> 7 | H23: =Inputs!$B$69 -> 7 | I23: =Inputs!$B$69 -> 7
A24: First-lien net leverage – covenant basis | B24: =IF(B9<=0,99,(B8-Projections!B55)/B9) -> 4.600609 | C24: =IF(C9<=0,99,(C8-Projections!C55)/C9) -> 4.2168362 | D24: =IF(D9<=0,99,(D8-Projections!D55)/D9) -> 3.8146035 | E24: =IF(E9<=0,99,(E8-Projections!E55)/E9) -> 3.4224459 | F24: =IF(F9<=0,99,(F8-Projections!F55)/F9) -> 3.0237167 | G24: =IF(G9<=0,99,(G8-Projections!G55)/G9) -> 2.6316334 | H24: =IF(H9<=0,99,(H8-Projections!H55)/H9) -> 2.2330854 | I24: =IF(I9<=0,99,(I8-Projections!I55)/I9) -> 1.8285217
A25: EBITDA cushion before covenant breach (%) | B25: =IF(B24<=0,1,1-B24/B23) -> 0.34277014 | C25: =IF(C24<=0,1,1-C24/C23) -> 0.39759484 | D25: =IF(D24<=0,1,1-D24/D23) -> 0.45505664 | E25: =IF(E24<=0,1,1-E24/E23) -> 0.51107916 | F25: =IF(F24<=0,1,1-F24/F23) -> 0.56804048 | G25: =IF(G24<=0,1,1-G24/G23) -> 0.62405237 | H25: =IF(H24<=0,1,1-H24/H23) -> 0.6809878 | I25: =IF(I24<=0,1,1-I24/I23) -> 0.73878261
A26: DISTRESS FLAGS (1 = triggered)
A27: FCCR below trigger | C27: =IF(C17<Inputs!$B$70,1,0) -> 0 | D27: =IF(D17<Inputs!$B$70,1,0) -> 0 | E27: =IF(E17<Inputs!$B$70,1,0) -> 0 | F27: =IF(F17<Inputs!$B$70,1,0) -> 0 | G27: =IF(G17<Inputs!$B$70,1,0) -> 0 | H27: =IF(H17<Inputs!$B$70,1,0) -> 0 | I27: =IF(I17<Inputs!$B$70,1,0) -> 0
A28: Total net leverage above trigger | C28: =IF(C12>Inputs!$B$71,1,0) -> 0 | D28: =IF(D12>Inputs!$B$71,1,0) -> 0 | E28: =IF(E12>Inputs!$B$71,1,0) -> 0 | F28: =IF(F12>Inputs!$B$71,1,0) -> 0 | G28: =IF(G12>Inputs!$B$71,1,0) -> 0 | H28: =IF(H12>Inputs!$B$71,1,0) -> 0 | I28: =IF(I12>Inputs!$B$71,1,0) -> 0
A29: Liquidity below trigger | C29: =IF(C20<Inputs!$B$72,1,0) -> 0 | D29: =IF(D20<Inputs!$B$72,1,0) -> 0 | E29: =IF(E20<Inputs!$B$72,1,0) -> 0 | F29: =IF(F20<Inputs!$B$72,1,0) -> 0 | G29: =IF(G20<Inputs!$B$72,1,0) -> 0 | H29: =IF(H20<Inputs!$B$72,1,0) -> 0 | I29: =IF(I20<Inputs!$B$72,1,0) -> 0
A30: First-lien covenant breached | C30: =IF(C24>C23,1,0) -> 0 | D30: =IF(D24>D23,1,0) -> 0 | E30: =IF(E24>E23,1,0) -> 0 | F30: =IF(F24>F23,1,0) -> 0 | G30: =IF(G24>G23,1,0) -> 0 | H30: =IF(H24>H23,1,0) -> 0 | I30: =IF(I24>I23,1,0) -> 0
A31: ANY DISTRESS | C31: =MAX(C27:C30) -> 0 | D31: =MAX(D27:D30) -> 0 | E31: =MAX(E27:E30) -> 0 | F31: =MAX(F27:F30) -> 0 | G31: =MAX(G27:G30) -> 0 | H31: =MAX(H27:H30) -> 0 | I31: =MAX(I27:I30) -> 0
A33: First year of distress | B33: =IFERROR(INDEX($C$4:$I$4,MATCH(1,$C$31:$I$31,0)),"None") -> None
A34: Years in distress (of 7) | B34: =SUM(C31:I31) -> 0
A35: Peak total net leverage | B35: =MAX(B12:I12) -> 7.6662003
A36: Minimum FCCR | B36: =MIN(C17:I17) -> 1.2878198
A37: Minimum liquidity | B37: =MIN(B20:I20) -> 554.005
A38: Peak total net leverage – Credit Agreement basis | B38: =MAX(B14:I14) -> 6.0713951
A39: Revolver drawn at revolver maturity (refinancing need) | B39: =INDEX(Projections!C38:I38,1,Inputs!D14) -> 0 | C39: =IF(B39>0,"Refinancing required before term loan maturity","No revolver balance at maturity") -> No revolver balance at maturity
A41: Distress flags (rows 27–29) use Underwriting EBITDA = economic distress. The covenant flag (row 30) uses Credit Agreement EBITDA = legal breach.
A42: How to read: run Inputs!B5 = 1, 2, 3 and Inputs!B7 = 1, 2. The R script stress-tests the same mechanics across thousands of paths to estimate PD.

Sheet Recovery
A1: Distressed Recovery Waterfall, LGD & Expected Loss ($mm)
A2: Default assumed at the start of the chosen projection year · Revolver assumed drawn at default · Unsecured residual shared pro rata
A4: DEFAULT ASSUMPTIONS
A5: Year of default (1–7) | B5: 3
A6: EBITDA decline from PF LTM Underwriting EBITDA at default | B6: 0.35
A7: Distressed EV / EBITDA multiple | B7: 6
A8: Administrative & professional fees (% of EV) | B8: 0.05
A9: Priority claims – taxes, wages ($mm) | B9: 30
A10: Revolver drawn at default (% of commitment) | B10: 1
A11: Trade payables & other unsecured claims | B11: =Historicals!F67 -> 639.767
A13: ENTERPRISE VALUE IN DEFAULT
A14: PF LTM Underwriting EBITDA | B14: =Historicals!G43 -> 403.85
A15: Distressed EBITDA | B15: =B14*(1-B6) -> 262.5025
A16: Distressed enterprise value | B16: =B15*B7 -> 1575.015
A17: – Administrative & professional fees | B17: =-B16*B8 -> -78.75075
A18: – Priority claims | B18: =-B9 -> -30
A19: Value available to secured creditors | B19: =MAX(0,SUM(B16:B18)) -> 1466.2642
A21: Waterfall | B21: Claim | C21: Recovered | D21: Recovery % | E21: Remaining value
A22: First lien: revolver (drawn) | B22: =Inputs!B14*B10 -> 500
A23: First lien: term loan B | B23: =INDEX(Projections!C40:I40,1,B5) -> 2275.2863
A24: Total first-lien claims | B24: =B22+B23 -> 2775.2863 | C24: =MIN(B24,B19) -> 1466.2642 | D24: =IF(B24=0,0,C24/B24) -> 0.528329 | E24: =B19-C24 -> 0
A25: Second-lien term loan | B25: =INDEX(Projections!C45:I45,1,B5) -> 0 | C25: =MIN(B25,E24) -> 0 | D25: =IF(B25=0,0,C25/B25) -> 0 | E25: =E24-C25 -> 0
A26: Unsecured pool:
A27: Senior unsecured notes | B27: =INDEX(Projections!C47:I47,1,B5) -> 750
A28: Trade payables & other unsecured | B28: =B11 -> 639.767
A29: First-lien deficiency claim | B29: =B24-C24 -> 1309.0221
A30: Second-lien deficiency claim | B30: =B25-C25 -> 0
A31: Total unsecured pool | B31: =SUM(B27:B30) -> 2698.7891 | C31: =MIN(B31,E25) -> 0 | D31: =IF(B31=0,0,C31/B31) -> 0 | E31: =E25-C31 -> 0
A32: Residual to equity | C32: =E31 -> 0
A34: RECOVERY BY CLASS
A35: First-lien TLB total recovery % (secured + share of unsecured) | B35: =IF(B24=0,0,(C24+B29*D31)/B24) -> 0.528329
A36: First-lien LGD (1 – recovery) | B36: =1-B35 -> 0.471671
A37: Second-lien recovery % | B37: =IF(B25=0,0,(C25+B30*D31)/B25) -> 0
A38: Senior unsecured notes recovery % | B38: =IF(B27=0,0,D31) -> 0
A39: Implied EV / total claims | B39: =IF((B24+B25+B27)=0,0,B16/(B24+B25+B27)) -> 0.44677647
A41: SENSITIVITY: FIRST-LIEN SECURED RECOVERY % (EBITDA decline × exit multiple)
A42: Exit multiple ↓ / EBITDA decline → | B42: 0.2 | C42: 0.25 | D42: 0.3 | E42: 0.35 | F42: 0.4 | G42: 0.45 | H42: 0.5
A43: 5 | B43: =IF($B$24=0,0,MIN(1,MAX(0,($B$14*(1-B$42)*$A43*(1-$B$8)-$B$9)/$B$24))) -> 0.54215307 | C43: =IF($B$24=0,0,MIN(1,MAX(0,($B$14*(1-C$42)*$A43*(1-$B$8)-$B$9)/$B$24))) -> 0.50759289 | D43: =IF($B$24=0,0,MIN(1,MAX(0,($B$14*(1-D$42)*$A43*(1-$B$8)-$B$9)/$B$24))) -> 0.47303272 | E43: =IF($B$24=0,0,MIN(1,MAX(0,($B$14*(1-E$42)*$A43*(1-$B$8)-$B$9)/$B$24))) -> 0.43847255 | F43: =IF($B$24=0,0,MIN(1,MAX(0,($B$14*(1-F$42)*$A43*(1-$B$8)-$B$9)/$B$24))) -> 0.40391238 | G43: =IF($B$24=0,0,MIN(1,MAX(0,($B$14*(1-G$42)*$A43*(1-$B$8)-$B$9)/$B$24))) -> 0.3693522 | H43: =IF($B$24=0,0,MIN(1,MAX(0,($B$14*(1-H$42)*$A43*(1-$B$8)-$B$9)/$B$24))) -> 0.33479203
A44: 5.5 | B44: =IF($B$24=0,0,MIN(1,MAX(0,($B$14*(1-B$42)*$A44*(1-$B$8)-$B$9)/$B$24))) -> 0.59744934 | C44: =IF($B$24=0,0,MIN(1,MAX(0,($B$14*(1-C$42)*$A44*(1-$B$8)-$B$9)/$B$24))) -> 0.55943315 | D44: =IF($B$24=0,0,MIN(1,MAX(0,($B$14*(1-D$42)*$A44*(1-$B$8)-$B$9)/$B$24))) -> 0.52141696 | E44: =IF($B$24=0,0,MIN(1,MAX(0,($B$14*(1-E$42)*$A44*(1-$B$8)-$B$9)/$B$24))) -> 0.48340077 | F44: =IF($B$24=0,0,MIN(1,MAX(0,($B$14*(1-F$42)*$A44*(1-$B$8)-$B$9)/$B$24))) -> 0.44538458 | G44: =IF($B$24=0,0,MIN(1,MAX(0,($B$14*(1-G$42)*$A44*(1-$B$8)-$B$9)/$B$24))) -> 0.40736839 | H44: =IF($B$24=0,0,MIN(1,MAX(0,($B$14*(1-H$42)*$A44*(1-$B$8)-$B$9)/$B$24))) -> 0.3693522
A45: 6 | B45: =IF($B$24=0,0,MIN(1,MAX(0,($B$14*(1-B$42)*$A45*(1-$B$8)-$B$9)/$B$24))) -> 0.65274562 | C45: =IF($B$24=0,0,MIN(1,MAX(0,($B$14*(1-C$42)*$A45*(1-$B$8)-$B$9)/$B$24))) -> 0.61127341 | D45: =IF($B$24=0,0,MIN(1,MAX(0,($B$14*(1-D$42)*$A45*(1-$B$8)-$B$9)/$B$24))) -> 0.5698012 | E45: =IF($B$24=0,0,MIN(1,MAX(0,($B$14*(1-E$42)*$A45*(1-$B$8)-$B$9)/$B$24))) -> 0.528329 | F45: =IF($B$24=0,0,MIN(1,MAX(0,($B$14*(1-F$42)*$A45*(1-$B$8)-$B$9)/$B$24))) -> 0.48685679 | G45: =IF($B$24=0,0,MIN(1,MAX(0,($B$14*(1-G$42)*$A45*(1-$B$8)-$B$9)/$B$24))) -> 0.44538458 | H45: =IF($B$24=0,0,MIN(1,MAX(0,($B$14*(1-H$42)*$A45*(1-$B$8)-$B$9)/$B$24))) -> 0.40391238
A46: 6.5 | B46: =IF($B$24=0,0,MIN(1,MAX(0,($B$14*(1-B$42)*$A46*(1-$B$8)-$B$9)/$B$24))) -> 0.70804189 | C46: =IF($B$24=0,0,MIN(1,MAX(0,($B$14*(1-C$42)*$A46*(1-$B$8)-$B$9)/$B$24))) -> 0.66311367 | D46: =IF($B$24=0,0,MIN(1,MAX(0,($B$14*(1-D$42)*$A46*(1-$B$8)-$B$9)/$B$24))) -> 0.61818544 | E46: =IF($B$24=0,0,MIN(1,MAX(0,($B$14*(1-E$42)*$A46*(1-$B$8)-$B$9)/$B$24))) -> 0.57325722 | F46: =IF($B$24=0,0,MIN(1,MAX(0,($B$14*(1-F$42)*$A46*(1-$B$8)-$B$9)/$B$24))) -> 0.528329 | G46: =IF($B$24=0,0,MIN(1,MAX(0,($B$14*(1-G$42)*$A46*(1-$B$8)-$B$9)/$B$24))) -> 0.48340077 | H46: =IF($B$24=0,0,MIN(1,MAX(0,($B$14*(1-H$42)*$A46*(1-$B$8)-$B$9)/$B$24))) -> 0.43847255
A47: 7 | B47: =IF($B$24=0,0,MIN(1,MAX(0,($B$14*(1-B$42)*$A47*(1-$B$8)-$B$9)/$B$24))) -> 0.76333817 | C47: =IF($B$24=0,0,MIN(1,MAX(0,($B$14*(1-C$42)*$A47*(1-$B$8)-$B$9)/$B$24))) -> 0.71495393 | D47: =IF($B$24=0,0,MIN(1,MAX(0,($B$14*(1-D$42)*$A47*(1-$B$8)-$B$9)/$B$24))) -> 0.66656969 | E47: =IF($B$24=0,0,MIN(1,MAX(0,($B$14*(1-E$42)*$A47*(1-$B$8)-$B$9)/$B$24))) -> 0.61818544 | F47: =IF($B$24=0,0,MIN(1,MAX(0,($B$14*(1-F$42)*$A47*(1-$B$8)-$B$9)/$B$24))) -> 0.5698012 | G47: =IF($B$24=0,0,MIN(1,MAX(0,($B$14*(1-G$42)*$A47*(1-$B$8)-$B$9)/$B$24))) -> 0.52141696 | H47: =IF($B$24=0,0,MIN(1,MAX(0,($B$14*(1-H$42)*$A47*(1-$B$8)-$B$9)/$B$24))) -> 0.47303272
A48: 7.5 | B48: =IF($B$24=0,0,MIN(1,MAX(0,($B$14*(1-B$42)*$A48*(1-$B$8)-$B$9)/$B$24))) -> 0.81863445 | C48: =IF($B$24=0,0,MIN(1,MAX(0,($B$14*(1-C$42)*$A48*(1-$B$8)-$B$9)/$B$24))) -> 0.76679419 | D48: =IF($B$24=0,0,MIN(1,MAX(0,($B$14*(1-D$42)*$A48*(1-$B$8)-$B$9)/$B$24))) -> 0.71495393 | E48: =IF($B$24=0,0,MIN(1,MAX(0,($B$14*(1-E$42)*$A48*(1-$B$8)-$B$9)/$B$24))) -> 0.66311367 | F48: =IF($B$24=0,0,MIN(1,MAX(0,($B$14*(1-F$42)*$A48*(1-$B$8)-$B$9)/$B$24))) -> 0.61127341 | G48: =IF($B$24=0,0,MIN(1,MAX(0,($B$14*(1-G$42)*$A48*(1-$B$8)-$B$9)/$B$24))) -> 0.55943315 | H48: =IF($B$24=0,0,MIN(1,MAX(0,($B$14*(1-H$42)*$A48*(1-$B$8)-$B$9)/$B$24))) -> 0.50759289
A49: 8 | B49: =IF($B$24=0,0,MIN(1,MAX(0,($B$14*(1-B$42)*$A49*(1-$B$8)-$B$9)/$B$24))) -> 0.87393072 | C49: =IF($B$24=0,0,MIN(1,MAX(0,($B$14*(1-C$42)*$A49*(1-$B$8)-$B$9)/$B$24))) -> 0.81863445 | D49: =IF($B$24=0,0,MIN(1,MAX(0,($B$14*(1-D$42)*$A49*(1-$B$8)-$B$9)/$B$24))) -> 0.76333817 | E49: =IF($B$24=0,0,MIN(1,MAX(0,($B$14*(1-E$42)*$A49*(1-$B$8)-$B$9)/$B$24))) -> 0.70804189 | F49: =IF($B$24=0,0,MIN(1,MAX(0,($B$14*(1-F$42)*$A49*(1-$B$8)-$B$9)/$B$24))) -> 0.65274562 | G49: =IF($B$24=0,0,MIN(1,MAX(0,($B$14*(1-G$42)*$A49*(1-$B$8)-$B$9)/$B$24))) -> 0.59744934 | H49: =IF($B$24=0,0,MIN(1,MAX(0,($B$14*(1-H$42)*$A49*(1-$B$8)-$B$9)/$B$24))) -> 0.54215307
A50: Grid excludes recovery on deficiency claims (secured value only), so it is slightly conservative vs B35.
A52: EXPECTED LOSS vs SPREAD (first-lien TLB)
A53: Cumulative PD over loan life (7 yrs) | B53: 0.2
A54: Loan life (years) | B54: 7
A55: Annualized PD | B55: =1-(1-B53)^(1/B54) -> 0.031374914
A56: LGD (from waterfall) | B56: =B36 -> 0.471671
A57: EAD – first-lien TLB at close | B57: =Cap_Stack!B11 -> 2400
A58: Annual expected loss (% of par) | B58: =B55*B56 -> 0.014798637
A59: Annual expected loss ($mm) | B59: =B58*B57 -> 35.516729
A60: Credit spread offered (over SOFR) | B60: =Inputs!B35 -> 0.0325
A61: + OID amortized over assumed 3-yr average life | B61: =Inputs!B19/3 -> 0.0033333333
A62: Total spread-equivalent compensation | B62: =B60+B61 -> 0.035833333
A63: Excess spread after expected loss | B63: =B62-B58 -> 0.021034696
A64: Break-even spread (covers expected loss only) | B64: =B58 -> 0.014798637
A65: Verdict (credit-loss lens) | B65: =IF(B63>0.015,"Spread comfortably covers expected loss",IF(B63>0,"Thin cushion – push for wider pricing","Spread does NOT cover expected loss")) -> Spread comfortably covers expected loss
A67: Excess spread must also pay for illiquidity, capital and model error – a ~150bps+ cushion is a reasonable minimum to target.
